{
	"book_title":"药症忌宜",
	"content":[
		{
			"type":"section",
			"title":"正文",
			"content":[
				{
					"detail":"风症",
					"type":"paragraph"
				},
				{
					"detail":"诸暴强直，支痛软戾，里急筋缩，皆属于风。真中风猝僵仆，口噤不言，不省人事，如遗尿直视，口开手撒，汗出如珠，属不治证。西北高寒之地有此，东南无之。",
					"type":"paragraph"
				},
				{
					"detail":"忌破气，下，吐，苦寒，酸敛，诸药俱录后。",
					"type":"paragraph"
				},
				{
					"detail":"宜辛甘发散，峻补真气。",
					"type":"paragraph"
				},
				{
					"detail":"桂枝附子甘草独活羌活天麻麻黄防风芎细辛本牛黄辛夷白芷蔓荆实牡荆实人参黄有痰加竹沥、南星、半夏、姜汁。",
					"type":"paragraph"
				},
				{
					"detail":"类中风",
					"type":"paragraph"
				},
				{
					"detail":"口眼歪斜，语言謇涩，半身不遂，口噤不言，四肢不举，痰涎壅盛，昏瞀不省人事。",
					"type":"paragraph"
				},
				{
					"detail":"忌汗，吐，下，大忌破气，温热，苦寒，及一切治风湿辛燥发散，并开窍走真气行血诸药，慎勿犯之，犯之则轻必重，重必毙。",
					"type":"paragraph"
				},
				{
					"detail":"麝香苏合香檀香龙脑香安息香余忌药俱录后。",
					"type":"paragraph"
				},
				{
					"detail":"宜滋补，阳虚者补气，阴虚者补血，阴阳两虚则气血双补，兼宜清热降气豁痰，及保脾胃。",
					"type":"paragraph"
				},
				{
					"detail":"天门冬（脾胃薄弱者勿多用）麦门冬荆沥苏子栝蒌根枇杷叶贝母霞天膏橘红甘草竹沥童便梨汁黄柏次益血于前药中加胡麻仁石斛生地黄牛膝薯蓣五味子甘菊花丹参枸杞子竹叶鳖甲菟丝子何首乌木瓜山茱萸芍药远志白蒺藜酸枣仁青蒿栝蒌仁沙参茯苓巴戟天柏子仁人参车前子茯神羚羊角如便闭加肉苁蓉、当归，倍麻仁，兼气虚加人参、黄，有肺热者，勿入人参。",
					"type":"paragraph"
				},
				{
					"detail":"感冒风寒",
					"type":"paragraph"
				},
				{
					"detail":"俗名伤风，其症或头疼身热，轻者则两鼻必塞，兼流清涕，必恶风寒，或声重或声哑，甚者痰壅气喘咳嗽。",
					"type":"paragraph"
				},
				{
					"detail":"忌补气，酸敛，闭气，诸药录后。",
					"type":"paragraph"
				},
				{
					"detail":"宜发散，辛甘，温。",
					"type":"paragraph"
				},
				{
					"detail":"芎细辛本防风甘草荆芥白芷前胡桔梗紫苏薄荷杏仁",
					"type":"paragraph"
				},
				{
					"detail":"伤风热",
					"type":"paragraph"
				},
				{
					"detail":"忌同感冒风寒。",
					"type":"paragraph"
				},
				{
					"detail":"宜辛寒，甘寒，发散。",
					"type":"paragraph"
				},
				{
					"detail":"石膏知母甘草竹叶麦冬前胡桔梗薄荷葛根桑白久而不愈者属虚，阳虚者加人参、黄，阴虚者加五味、地黄，倍麦冬、白芍。",
					"type":"paragraph"
				},
				{
					"detail":"寒症诸病",
					"type":"paragraph"
				},
				{
					"detail":"上下所出水液，澄澈清冷，瘕疝坚痞，腹满急痛，下利清白，食已不饥，吐利腥秽，屈伸不便，厥逆禁固，皆属于寒。凡中寒必本于阳虚。",
					"type":"paragraph"
				},
				{
					"detail":"忌破气，苦寒，下，苦寒，辛寒诸药录后。",
					"type":"paragraph"
				},
				{
					"detail":"宜补气，散寒，辛甘，温热，轻者解表，重者温补。",
					"type":"paragraph"
				},
				{
					"detail":"桂枝干姜麻黄人参附子黄伤寒冬月即病，宜从仲景法。",
					"type":"paragraph"
				},
				{
					"detail":"暑症诸病",
					"type":"paragraph"
				},
				{
					"detail":"喘呕暴注下迫，霍乱转筋，身热瞀郁，小便浊赤，皆属于暑。",
					"type":"paragraph"
				},
				{
					"detail":"忌破气，升，复忌下，湿润，辛温，辛燥，热散，闭气，热，诸药录后。",
					"type":"paragraph"
				},
				{
					"detail":"宜清暑益气，健脾，甘寒，苦温，辛寒，酸寒，苦寒。",
					"type":"paragraph"
				},
				{
					"detail":"黄连香薷葛根石膏知母甘草人参黄白术扁豆神曲橘皮茯苓木瓜麦门五味白芍白梅乌梅大约用清暑益气汤、香薷饮、生脉散。凡病暑之人，其气必虚，暑伤气，无气以动，故当补气为本。惟肺热多火者，忌参、术。",
					"type":"paragraph"
				},
				{
					"detail":"中暑",
					"type":"paragraph"
				},
				{
					"detail":"猝昏晕，急以童便入即省。",
					"type":"paragraph"
				},
				{
					"detail":"忌宜俱同暑。",
					"type":"paragraph"
				},
				{
					"detail":"又方用丝瓜叶一片，白盐梅肉一枚，并取核中仁，共研如泥，新汲水调灌立瘥，兼治中暑霍乱如神。",
					"type":"paragraph"
				},
				{
					"detail":"太阳病中",
					"type":"paragraph"
				},
				{
					"detail":"忌同暑。",
					"type":"paragraph"
				},
				{
					"detail":"宜人参白虎汤。有肺病不能服参者，用竹叶石膏汤。脾胃作泻者，水调六一散。",
					"type":"paragraph"
				},
				{
					"detail":"霍乱",
					"type":"paragraph"
				},
				{
					"detail":"见胃虚条内。",
					"type":"paragraph"
				},
				{
					"detail":"忌宜俱同暑。",
					"type":"paragraph"
				},
				{
					"detail":"疰夏",
					"type":"paragraph"
				},
				{
					"detail":"繇于脾胃薄弱，胃家有湿热，及留饮所致。",
					"type":"paragraph"
				},
				{
					"detail":"忌同前。",
					"type":"paragraph"
				},
				{
					"detail":"宜益气健脾，酸寒，苦寒，淡渗。",
					"type":"paragraph"
				},
				{
					"detail":"人参半夏白术橘皮茯苓扁豆白芍木瓜泽泻兼服生脉散",
					"type":"paragraph"
				},
				{
					"detail":"湿症",
					"type":"paragraph"
				},
				{
					"detail":"诸痉强直，积饮痞膈中满，霍乱吐下，体重肿，肉如泥，按之不起，皆属于湿。经云∶地之湿气，感则害人。皮肉筋脉，故其病筋骨疼痛，腰重痛，不可转侧，身重四肢不利。湿在上，病呕吐头重胸满。湿在中，腹胀中满泄泻。湿在下，足腔跗肿，脚气疮久不愈。",
					"type":"paragraph"
				},
				{
					"detail":"忌湿润，甘，咸，诸药录后。",
					"type":"paragraph"
				},
				{
					"detail":"宜散，渗泄，燥，辛，苦。",
					"type":"paragraph"
				},
				{
					"detail":"木瓜薏苡苍术石斛萆石菖蒲茯苓佐以防风、葛根，寒湿加半夏、五加皮，风湿加独活，湿热加黄柏、车前子、木通，甚者汉防己。",
					"type":"paragraph"
				},
				{
					"detail":"香港脚",
					"type":"paragraph"
				},
				{
					"detail":"繇于湿热。",
					"type":"paragraph"
				},
				{
					"detail":"忌温燥，湿热，补气，复忌破气，升，诸药录后。",
					"type":"paragraph"
				},
				{
					"detail":"宜清热，除湿，利小便，甘平，酸寒，苦寒，辛温，淡渗。",
					"type":"paragraph"
				},
				{
					"detail":"黄柏石斛麦门冬木瓜茯苓石菖蒲木通泽泻薏苡仁萆防己车前子",
					"type":"paragraph"
				},
				{
					"detail":"燥症",
					"type":"paragraph"
				},
				{
					"detail":"诸涩枯涸，干劲皴揭，皆属于燥。角弓反张，筋挛急不舒，舌强不能言，二便闭涩，口渴口干，舌苦，皮肤皴揭，毛发脆折，津液不生，血枯胃槁，以致饮食不化，噎膈吐食。",
					"type":"paragraph"
				},
				{
					"detail":"忌升散，破气，下，辛燥，大热，温，药录后。",
					"type":"paragraph"
				},
				{
					"detail":"宜润，益血，辛，甘寒，酸寒，咸寒，有热症者，宜兼清热。",
					"type":"paragraph"
				},
				{
					"detail":"当归地黄麦门冬人乳牛乳肉苁蓉酥蜜甘菊花胡桃麻仁柏子仁人参胡麻天门冬松实蔗浆五味子白芍枣仁芦根汁梨汁韭汁童便佐以姜汁",
					"type":"paragraph"
				},
				{
					"detail":"火症",
					"type":"paragraph"
				},
				{
					"detail":"诸热瞀，暴喑冒昧，躁扰狂越，骂詈惊骇，肿疼酸，气逆上冲，禁栗如丧神守，嚏呕疮疡，喉痹耳鸣及聋，呕涌溢，食不下，目昧不明，暴注，暴病暴死，皆属于火。",
					"type":"paragraph"
				},
				{
					"detail":"忌补敛，升发，闭气，辛燥，温热，诸药录后。",
					"type":"paragraph"
				},
				{
					"detail":"宜降折，下，咸寒，苦寒，辛寒，甘寒。",
					"type":"paragraph"
				},
				{
					"detail":"大黄童便芒硝黄芩黄连黄柏连翘石膏山栀玄参甘草知母天冬麦冬生地蓝汁虚者宜甘寒咸寒以滋水，不宜用苦寒伤胃。",
					"type":"paragraph"
				},
				{
					"detail":"猝眩仆",
					"type":"paragraph"
				},
				{
					"detail":"九窍流血，多不治。",
					"type":"paragraph"
				},
				{
					"detail":"忌同火。",
					"type":"paragraph"
				},
				{
					"detail":"宜童便、盐汤、竹沥、蓝汁、梨汁、生犀角汁。",
					"type":"paragraph"
				},
				{
					"detail":"猝心痛",
					"type":"paragraph"
				},
				{
					"detail":"忌同火。",
					"type":"paragraph"
				},
				{
					"detail":"宜山栀白芍药玄胡索生甘草盐汤苏子",
					"type":"paragraph"
				},
				{
					"detail":"目暴赤肿痛甚",
					"type":"paragraph"
				},
				{
					"detail":"见肝实条内。",
					"type":"paragraph"
				},
				{
					"detail":"忌宜俱同。",
					"type":"paragraph"
				},
				{
					"detail":"二便忽闭",
					"type":"paragraph"
				},
				{
					"detail":"以利小便为先。",
					"type":"paragraph"
				},
				{
					"detail":"忌同火。",
					"type":"paragraph"
				},
				{
					"detail":"宜降润，苦寒，甘寒，辛寒，利窍。",
					"type":"paragraph"
				},
				{
					"detail":"大黄苏子生蜜麻仁桃仁石膏知母天冬麦冬黄芩山栀滑石泽泻猪苓车前木通",
					"type":"paragraph"
				},
				{
					"detail":"头面赤肿",
					"type":"paragraph"
				},
				{
					"detail":"忌同火。",
					"type":"paragraph"
				},
				{
					"detail":"宜清热解毒，发散，苦寒，辛寒，甘寒，咸寒。",
					"type":"paragraph"
				},
				{
					"detail":"甘菊花鼠粘子连翘荆芥薄荷蝉蜕大黄玄参石膏知母竹叶童便生甘草",
					"type":"paragraph"
				},
				{
					"detail":"忽大渴思冰水",
					"type":"paragraph"
				},
				{
					"detail":"忌同火。",
					"type":"paragraph"
				},
				{
					"detail":"宜润，生津液，辛寒，甘寒，咸寒。",
					"type":"paragraph"
				},
				{
					"detail":"石膏知母玄参麦冬竹叶栝蒌根梨汁蔗浆童便凉水冰五味子",
					"type":"paragraph"
				},
				{
					"detail":"口干舌苦",
					"type":"paragraph"
				},
				{
					"detail":"忌宜俱同火。",
					"type":"paragraph"
				},
				{
					"detail":"暴喑",
					"type":"paragraph"
				},
				{
					"detail":"忌同火。",
					"type":"paragraph"
				},
				{
					"detail":"宜降气，发音声，苦，苦寒，辛凉，咸寒。",
					"type":"paragraph"
				},
				{
					"detail":"苏子枇杷叶贝母桔梗百部竹沥梨汁天门冬甘草薄荷玄参童便麦冬桑白皮",
					"type":"paragraph"
				},
				{
					"detail":"暴注",
					"type":"paragraph"
				},
				{
					"detail":"忌同火。",
					"type":"paragraph"
				},
				{
					"detail":"宜利水，苦寒，酸寒。",
					"type":"paragraph"
				},
				{
					"detail":"茯苓黄连黄芩白芍药生甘草葛根滑石木通虚者加人参、白扁豆、莲肉。",
					"type":"paragraph"
				},
				{
					"detail":"躁扰狂越，骂詈惊骇",
					"type":"paragraph"
				},
				{
					"detail":"忌同火。",
					"type":"paragraph"
				},
				{
					"detail":"宜清镇，苦寒，辛寒，咸寒。",
					"type":"paragraph"
				},
				{
					"detail":"丹砂牛黄黄连黄芩山栀滑石石膏知母童便大便闭者加大黄下之，不行加芒硝。",
					"type":"paragraph"
				},
				{
					"detail":"禁栗如丧神守",
					"type":"paragraph"
				},
				{
					"detail":"忌同火。",
					"type":"paragraph"
				},
				{
					"detail":"宜同躁扰狂越。",
					"type":"paragraph"
				},
				{
					"detail":"气逆冲上。",
					"type":"paragraph"
				},
				{
					"detail":"忌同火。",
					"type":"paragraph"
				},
				{
					"detail":"宜降气，酸敛，甘寒，苦寒，咸寒。",
					"type":"paragraph"
				},
				{
					"detail":"苏子枇杷叶橘红五味子石斛番降香黄柏山茱萸牛膝白芍药童便桑白皮麦冬",
					"type":"paragraph"
				},
				{
					"detail":"瞀",
					"type":"paragraph"
				},
				{
					"detail":"忌同火。",
					"type":"paragraph"
				},
				{
					"detail":"宜清热和肝，酸寒，苦寒，辛寒，甘寒。",
					"type":"paragraph"
				},
				{
					"detail":"白芍药生甘草竹叶玄参黄连生地黄甘菊花麦门冬知母石膏以上忌宜为风寒暑湿燥火六淫外症，下乃阴阳五脏六腑里虚实内症之忌宜也。",
					"type":"paragraph"
				},
				{
					"detail":"阳虚",
					"type":"paragraph"
				},
				{
					"detail":"即真气虚，其证恶寒，或发热自汗，汗多亡阳，阳虚不发热，单恶寒者居多。",
					"type":"paragraph"
				},
				{
					"detail":"忌破气，降泄，利水，苦寒，又忌辛热发散。",
					"type":"paragraph"
				},
				{
					"detail":"青皮枳壳浓朴牵牛槟榔（以上破气）大黄石膏山栀知母天冬生地栝蒌（以上降泄）泽泻木通瞿麦汉防己海金沙葶苈猪苓滑石（以上利水）黄芩黄连黄柏玄参槐花（以上苦寒）芍药乌梅醋（以上酸）麻黄羌活独活前胡防风荆芥吴茱萸（以上辛热发散）宜补，甘，温，热。",
					"type":"paragraph"
				},
				{
					"detail":"人参黄二术炙草当归桂淫羊藿附子仙茅鹿茸羊肉补骨脂巴戟天",
					"type":"paragraph"
				},
				{
					"detail":"阴虚",
					"type":"paragraph"
				},
				{
					"detail":"即精血虚，其证为咳嗽多痰，吐血咯血嗽血，鼻衄齿衄，盗汗自汗，发热寒热潮热，骨乏无力，不眠气急，腰背痛。",
					"type":"paragraph"
				},
				{
					"detail":"忌补气，复忌破气，燥热辛温，又忌大寒大苦伤胃，并升提发散，利水。",
					"type":"paragraph"
				},
				{
					"detail":"人参黄二术（以上补气）南星半夏附子官桂桂枝仙茅鹿茸干姜丁香胡椒乌头火酒吴萸乌药生姜（以上燥热辛温）山栀黄芩黄连大黄芒硝玄明粉（以上大寒大苦伤胃）麻黄升麻柴胡羌活独活本川芎防风（以上升提发热）破气利水药录后。",
					"type":"paragraph"
				},
				{
					"detail":"宜生精补血，兼清虚热，敛摄，酸寒，甘寒，甘平，咸寒，略兼苦寒。",
					"type":"paragraph"
				},
				{
					"detail":"地黄柏仁人乳沙苑蒺藜枸杞子牛膝麋角胶阿胶酸枣仁沙参石斛白芍药山茱萸远志地骨皮薯蓣续断车前子五味子鳖甲麦门冬黄柏知母牡丹皮",
					"type":"paragraph"
				},
				{
					"detail":"表虚",
					"type":"paragraph"
				},
				{
					"detail":"其证自汗恶风，洒淅寒，喜就温暖，脉浮无力。",
					"type":"paragraph"
				},
				{
					"detail":"忌破气，升发，辛热。",
					"type":"paragraph"
				},
				{
					"detail":"麻黄升麻防风柴胡羌活独活前胡干葛紫苏薄荷白芷生姜荆芥（以上升发）吴萸桂枝（表虚而中寒者不忌）干姜（以上辛热）破气药见后。",
					"type":"paragraph"
				},
				{
					"detail":"宜补敛，益气实表，甘，酸。",
					"type":"paragraph"
				},
				{
					"detail":"人参黄芍药甘草桂枝（有热者勿用）五味子",
					"type":"paragraph"
				},
				{
					"detail":"里虚",
					"type":"paragraph"
				},
				{
					"detail":"其证洞泄，或完谷不化，心腹痛，按之即止，或腹胀，或伤寒，下后痞满。",
					"type":"paragraph"
				},
				{
					"detail":"忌破气，下，苦寒。",
					"type":"paragraph"
				},
				{
					"detail":"大黄芒硝玄明粉牵牛（已上下）黄芩黄连山栀天门冬防己知母（上苦寒）破气药录后。",
					"type":"paragraph"
				},
				{
					"detail":"宜温补，甘，佐以辛热。",
					"type":"paragraph"
				},
				{
					"detail":"人参术炙甘草大枣糯米肉桂附子（有热者勿用）干姜",
					"type":"paragraph"
				},
				{
					"detail":"阳实",
					"type":"paragraph"
				},
				{
					"detail":"即表邪热盛，其证头痛寒热，遍身骨痛无力。",
					"type":"paragraph"
				},
				{
					"detail":"忌补敛，下，大热。",
					"type":"paragraph"
				},
				{
					"detail":"黄人参二术桂枝芍药五味醋米面食猪羊犬（以上补敛）附子胡椒干姜肉桂蒜吴茱萸（以上大热）下药录后。",
					"type":"paragraph"
				},
				{
					"detail":"宜辛寒发散，天寒略加辛热辛温佐之。",
					"type":"paragraph"
				},
				{
					"detail":"石膏知母葛根麦冬前胡柴胡黄芩紫苏薄荷升麻防风葱白荆芥羌活麻黄（冬月可用春夏忌之）",
					"type":"paragraph"
				},
				{
					"detail":"阴实",
					"type":"paragraph"
				},
				{
					"detail":"即里实，外感证属邪热内结者，其证胸腹硬痛，手不可近，大便七八日不行，或挟热下痢。",
					"type":"paragraph"
				},
				{
					"detail":"忌辛温发散，补敛，药见上。",
					"type":"paragraph"
				},
				{
					"detail":"宜下，苦寒，咸寒，甘辛。",
					"type":"paragraph"
				},
				{
					"detail":"大黄浓朴枳实滑石山栀黄芩黄连蓝茵陈芒硝桃仁",
					"type":"paragraph"
				},
				{
					"detail":"阳厥",
					"type":"paragraph"
				},
				{
					"detail":"即热厥，其证四肢厥逆，身热面赤，唇燥大渴，口干舌苦，目闭或不闭，小便赤涩短少，大便燥结，不省人事。",
					"type":"paragraph"
				},
				{
					"detail":"忌升发，补敛，燥热辛温，诸药俱录后。",
					"type":"paragraph"
				},
				{
					"detail":"宜下，清热，甘寒，苦寒，咸寒。",
					"type":"paragraph"
				},
				{
					"detail":"大黄芒硝石膏黄芩黄连山栀知母童便如挟虚有痰者，宜麦门冬、竹沥、芦根汁、梨汁、牛黄、童便，如妇人热入血室，因而厥者，药中以童便为君，加赤芍药、生地黄、牛膝、牡丹皮、桃仁，甚者大便结燥，加大黄、芒硝下之，通即止，勿尽剂。",
					"type":"paragraph"
				},
				{
					"detail":"阴厥",
					"type":"paragraph"
				},
				{
					"detail":"即寒厥，其证四肢厥逆，身冷面青，蜷卧，手指爪青黯，腹痛大便溏，或完谷不化，小便自利，不渴，不省人事。",
					"type":"paragraph"
				},
				{
					"detail":"忌下，破气，苦寒，咸寒，酸寒。",
					"type":"paragraph"
				},
				{
					"detail":"食盐童便（以上咸寒）芍药醋（以上酸寒）下破气苦寒药录后。",
					"type":"paragraph"
				},
				{
					"detail":"宜补气，温中，甘温，辛热。",
					"type":"paragraph"
				},
				{
					"detail":"人参干姜附子桂吴茱萸",
					"type":"paragraph"
				},
				{
					"detail":"上盛下虚",
					"type":"paragraph"
				},
				{
					"detail":"属阳盛阴虚。",
					"type":"paragraph"
				},
				{
					"detail":"忌升散，下，助阳补气，复忌破气，燥热辛。",
					"type":"paragraph"
				},
				{
					"detail":"宜降，益阴，甘寒，酸寒，佐以咸寒，苦寒。",
					"type":"paragraph"
				},
				{
					"detail":"苏子生地沙参牛膝枇杷叶枸杞子麦冬天冬白芍玄参山茱萸五味子黄柏童便",
					"type":"paragraph"
				},
				{
					"detail":"心虚",
					"type":"paragraph"
				},
				{
					"detail":"（八证）忌升发，破气，苦寒，辛燥，大热，诸药录后。",
					"type":"paragraph"
				},
				{
					"detail":"宜补血，甘温，酸敛，佐以咸寒，镇坠。",
					"type":"paragraph"
				},
				{
					"detail":"生地黄龙眼肉人参石斛丹参茯神炙甘草酸枣仁五味柏仁远志炒盐",
					"type":"paragraph"
				},
				{
					"detail":"癫痫惊邪",
					"type":"paragraph"
				},
				{
					"detail":"属心气虚，兼有热痰。",
					"type":"paragraph"
				},
				{
					"detail":"忌同上。",
					"type":"paragraph"
				},
				{
					"detail":"宜清热豁痰，合心虚加麦门冬犀角羚羊角竹沥天竺黄牛黄胆星贝母琥珀金箔",
					"type":"paragraph"
				},
				{
					"detail":"心烦不得眠",
					"type":"paragraph"
				},
				{
					"detail":"属心血虚有热。",
					"type":"paragraph"
				},
				{
					"detail":"忌同上。",
					"type":"paragraph"
				},
				{
					"detail":"宜养阴血清热，加白芍药玄参黄连淡竹叶沙参",
					"type":"paragraph"
				},
				{
					"detail":"怔忡",
					"type":"paragraph"
				},
				{
					"detail":"心澹澹动，盗汗属心血虚，汗者心之液也。",
					"type":"paragraph"
				},
				{
					"detail":"忌同上。",
					"type":"paragraph"
				},
				{
					"detail":"宜补敛清热，合心虚加当归黄芍药黄芩黄柏",
					"type":"paragraph"
				},
				{
					"detail":"伏梁",
					"type":"paragraph"
				},
				{
					"detail":"属心经气血虚，以致邪留不去。",
					"type":"paragraph"
				},
				{
					"detail":"忌破血，汗，下。",
					"type":"paragraph"
				},
				{
					"detail":"三棱蓬莪姜黄虻虫红蓝花水蛭桃仁（以上破血）诸药录后。",
					"type":"paragraph"
				},
				{
					"detail":"宜活血，凉血，散热通结，辛咸。",
					"type":"paragraph"
				},
				{
					"detail":"当归乳香五灵脂没药赤芍药郁金远志菖蒲玄胡索茯神参用东垣伏梁丸治之。",
					"type":"paragraph"
				},
				{
					"detail":"肝虚",
					"type":"paragraph"
				},
				{
					"detail":"（十证）忌收敛，破气，苦寒，下，诸药录后。",
					"type":"paragraph"
				},
				{
					"detail":"宜辛散，甘缓。",
					"type":"paragraph"
				},
				{
					"detail":"当归陈皮生姜地黄甘菊甘草胡麻谷精草决明子刺蒺藜因郁而虚者加细辛、缩砂密、沉水香、川芎、香附。",
					"type":"paragraph"
				},
				{
					"detail":"转筋",
					"type":"paragraph"
				},
				{
					"detail":"属血虚。",
					"type":"paragraph"
				},
				{
					"detail":"忌下，复忌升，燥热，闭气，苦寒，破气。",
					"type":"paragraph"
				},
				{
					"detail":"二术黄银杏猪脂羊肉面（以上闭气）宜酸，辛，甘平。",
					"type":"paragraph"
				},
				{
					"detail":"木瓜牛膝当归身石斛续断陈皮芍药炙草缩砂密",
					"type":"paragraph"
				},
				{
					"detail":"目昏目光短",
					"type":"paragraph"
				},
				{
					"detail":"属肝血虚，及肾水真阴不足。",
					"type":"paragraph"
				},
				{
					"detail":"忌破气，升，燥热，诸药录后。",
					"type":"paragraph"
				},
				{
					"detail":"宜补肝兼滋肾，甘温益血，甘寒除热。",
					"type":"paragraph"
				},
				{
					"detail":"甘枸杞生地黄甘菊花沙苑蒺藜谷精草五味子决明子天门冬麦门冬",
					"type":"paragraph"
				},
				{
					"detail":"目翳",
					"type":"paragraph"
				},
				{
					"detail":"属肝热，兼肾水不足。",
					"type":"paragraph"
				},
				{
					"detail":"忌破气，升，燥热，苦寒，诸药录后。",
					"type":"paragraph"
				},
				{
					"detail":"宜补肝血，除热，退翳。",
					"type":"paragraph"
				},
				{
					"detail":"甘菊花生地黄决明子石决明沙苑蒺藜羚羊角犀角黄连伏翼粪木贼谷精草密蒙花人爪蝉蜕石蟹真珠琥珀",
					"type":"paragraph"
				},
				{
					"detail":"亡血过多",
					"type":"paragraph"
				},
				{
					"detail":"角弓反张，或小腹连阴作痛，属肝血虚有热。",
					"type":"paragraph"
				},
				{
					"detail":"忌同肝血虚。",
					"type":"paragraph"
				},
				{
					"detail":"宜补血清热，甘寒，甘温，酸寒，咸寒，辛润。",
					"type":"paragraph"
				},
				{
					"detail":"当归生地黄白芍药炙草牛膝麦冬童便牡丹皮甘菊花有汗加人参、黄、枣仁、五味子。",
					"type":"paragraph"
				},
				{
					"detail":"偏头痛",
					"type":"paragraph"
				},
				{
					"detail":"属血虚，肝家有热不急治，久之必损目。",
					"type":"paragraph"
				},
				{
					"detail":"忌同目昏。",
					"type":"paragraph"
				},
				{
					"detail":"宜养血，清虚热，甘寒，酸寒，辛寒。",
					"type":"paragraph"
				},
				{
					"detail":"生地黄天门冬甘菊花白芍药当归川芍乌梅炙甘草土茯苓金银藤黑豆有火实者加黄连（酒炒）大黄（酒蒸）芎石膏雨前茶。",
					"type":"paragraph"
				},
				{
					"detail":"目黑暗眩晕",
					"type":"paragraph"
				},
				{
					"detail":"属血虚，兼肾水真阴不足。",
					"type":"paragraph"
				},
				{
					"detail":"忌同上。",
					"type":"paragraph"
				},
				{
					"detail":"宜养血补肝，清热，甘寒，甘平，酸寒，苦寒。",
					"type":"paragraph"
				},
				{
					"detail":"生地黄枸杞子甘菊花五味子白蒺藜当归薯蓣甘草山茱萸白芍药天门冬黄柏",
					"type":"paragraph"
				},
				{
					"detail":"肥气",
					"type":"paragraph"
				},
				{
					"detail":"属气血两虚，肝气不和，逆气与瘀血相并而成。",
					"type":"paragraph"
				},
				{
					"detail":"忌同上苦寒。",
					"type":"paragraph"
				},
				{
					"detail":"宜和肝散结气，兼行气血凝滞，甘温，甘平。",
					"type":"paragraph"
				},
				{
					"detail":"川芎当归沉香干姜肉桂橘皮红花郁金玄胡索赤芍药香附山楂红曲砂仁参用东垣肥气丸治之。",
					"type":"paragraph"
				},
				{
					"detail":"脾虚",
					"type":"paragraph"
				},
				{
					"detail":"（十二证）忌下，降泄，破气，苦寒，诸药录后。",
					"type":"paragraph"
				},
				{
					"detail":"宜甘温，佐以辛香，酸平。",
					"type":"paragraph"
				},
				{
					"detail":"人参大枣黄薯蓣炙甘草白茯苓莲肉橘红薷香木瓜白扁豆白豆蔻白芍枣仁",
					"type":"paragraph"
				},
				{
					"detail":"饮食劳倦伤脾",
					"type":"paragraph"
				},
				{
					"detail":"发热，或饮食不消化，补药中加麦、谷。",
					"type":"paragraph"
				},
				{
					"detail":"忌破气，消导克伐，苦寒，复忌燥。",
					"type":"paragraph"
				},
				{
					"detail":"草果枳实槟榔蓬莪三棱宜补中益气，甘温，升，酸。",
					"type":"paragraph"
				},
				{
					"detail":"人参黄术炙甘草大枣白芍药柴胡升麻石斛麦门冬橘红酸枣仁",
					"type":"paragraph"
				},
				{
					"detail":"停饮",
					"type":"paragraph"
				},
				{
					"detail":"为恣饮汤水，或冷茶冷酒所致。",
					"type":"paragraph"
				},
				{
					"detail":"忌下，酸敛，湿润，滞腻。",
					"type":"paragraph"
				},
				{
					"detail":"桃仁郁李仁宜健脾利水，淡渗，兼辛散。",
					"type":"paragraph"
				},
				{
					"detail":"人参白术半夏茯苓橘皮泽泻猪苓木通桑白皮旋复花紫苏白豆蔻",
					"type":"paragraph"
				},
				{
					"detail":"水肿",
					"type":"paragraph"
				},
				{
					"detail":"属脾气虚。",
					"type":"paragraph"
				},
				{
					"detail":"忌破气，下泄，湿润，咸，苦寒。",
					"type":"paragraph"
				},
				{
					"detail":"食盐商陆（以上咸）诸药录后。",
					"type":"paragraph"
				},
				{
					"detail":"宜补脾益气，燥湿，利水，辛香，甘温，佐以淡渗。",
					"type":"paragraph"
				},
				{
					"detail":"人参二术薏苡仁橘皮薯蓣桑白皮木瓜茯苓赤小豆香薷猪苓缩砂密泽泻姜皮",
					"type":"paragraph"
				},
				{
					"detail":"脾虚中满",
					"type":"paragraph"
				},
				{
					"detail":"属脾气虚，兼脾阴虚。",
					"type":"paragraph"
				},
				{
					"detail":"忌破气，下，消导，利水，甘。",
					"type":"paragraph"
				},
				{
					"detail":"饴糖大枣蜜甘草（以上甘）诸药录后。",
					"type":"paragraph"
				},
				{
					"detail":"昼剧夜静，属脾气虚，宜补气健脾，甘温，淡渗，佐以辛香。",
					"type":"paragraph"
				},
				{
					"detail":"人参二术白芍药茯苓橘皮桑白皮姜皮藿香车前子缩砂密无热证佐以桂。",
					"type":"paragraph"
				},
				{
					"detail":"夜剧昼静，属脾阴虚，宜补脾阴，兼制肝清热，甘平，酸寒，淡渗。",
					"type":"paragraph"
				},
				{
					"detail":"酸枣仁石斛莲肉白芍药橘皮白扁豆五味子苏子木瓜桑白皮茯苓车前子",
					"type":"paragraph"
				},
				{
					"detail":"噎膈",
					"type":"paragraph"
				},
				{
					"detail":"属气血两虚，繇于血液衰少，而非痰气壅逆所成。",
					"type":"paragraph"
				},
				{
					"detail":"忌破气，升，复忌下，消导，燥，苦寒，辛热。",
					"type":"paragraph"
				},
				{
					"detail":"宜降，清热润燥，甘温甘平以益血，佐辛香顺气。",
					"type":"paragraph"
				},
				{
					"detail":"苏子橘红枇杷叶人参白芍药酸枣仁人乳牛乳芦根汁姜汁龙眼肉白豆蔻蔗浆梨汁韭汁",
					"type":"paragraph"
				},
				{
					"detail":"脾泄",
					"type":"paragraph"
				},
				{
					"detail":"属气虚。",
					"type":"paragraph"
				},
				{
					"detail":"忌破气，下，消导，苦寒，诸药录后。",
					"type":"paragraph"
				},
				{
					"detail":"宜温中补气，升清，甘温，甘平，佐以辛香。",
					"type":"paragraph"
				},
				{
					"detail":"人参白术炙甘草薯蓣白扁豆车前子莲肉茯苓白芍药升麻肉豆蔻缩砂密柴胡橘皮白莱菔木香丁香藿香兼有湿及痰，经年不愈，粪色白者，须服丸制松脂。",
					"type":"paragraph"
				},
				{
					"detail":"健忘",
					"type":"paragraph"
				},
				{
					"detail":"属气血两虚。",
					"type":"paragraph"
				},
				{
					"detail":"忌升，燥热，复忌苦寒，辛散，诸药录后。",
					"type":"paragraph"
				},
				{
					"detail":"宜益脾阴，兼补气，酸敛，甘温，甘寒，辛平，通窍。",
					"type":"paragraph"
				},
				{
					"detail":"酸枣仁白芍药人参黄丹参炙甘草五味子龙眼肉茯神远志柏子仁麦门冬石菖蒲茯苓",
					"type":"paragraph"
				},
				{
					"detail":"倦怠嗜卧",
					"type":"paragraph"
				},
				{
					"detail":"属脾气不足。",
					"type":"paragraph"
				},
				{
					"detail":"忌破气，消导，苦寒。",
					"type":"paragraph"
				},
				{
					"detail":"宜补气，兼健脾，甘温，辛香。",
					"type":"paragraph"
				},
				{
					"detail":"人参白术炙甘草黄茯苓白扁豆薯蓣谷缩砂密橘皮藿香白豆蔻",
					"type":"paragraph"
				},
				{
					"detail":"脾虚腹痛",
					"type":"paragraph"
				},
				{
					"detail":"按之则止，属血虚。",
					"type":"paragraph"
				},
				{
					"detail":"忌破气，破血，香燥，苦寒，诸药录后。",
					"type":"paragraph"
				},
				{
					"detail":"宜益气补血，甘温，酸平。",
					"type":"paragraph"
				},
				{
					"detail":"酸枣仁炙甘草人参大枣石斛龙眼肉麦门冬白芍药",
					"type":"paragraph"
				},
				{
					"detail":"痞气",
					"type":"paragraph"
				},
				{
					"detail":"属脾气虚，及气郁所致。",
					"type":"paragraph"
				},
				{
					"detail":"忌破气，下，湿润，苦寒。",
					"type":"paragraph"
				},
				{
					"detail":"宜健脾，兼散结滞，甘温，辛香。",
					"type":"paragraph"
				},
				{
					"detail":"人参白芍橘红缩砂密藿香谷麦红曲香附吴茱萸木香（参东垣痞气丸治之）",
					"type":"paragraph"
				},
				{
					"detail":"肺虚",
					"type":"paragraph"
				},
				{
					"detail":"（七证）忌补气，升散，辛燥，温热，诸药录后。",
					"type":"paragraph"
				},
				{
					"detail":"宜清热，降气，酸敛，润燥。",
					"type":"paragraph"
				},
				{
					"detail":"贝母苏子沙参百部天门冬麦门冬百合杏仁蜜梨柿枇杷叶桑白五味五倍子无热加人参。",
					"type":"paragraph"
				},
				{
					"detail":"喘",
					"type":"paragraph"
				},
				{
					"detail":"属肺虚有热，因而痰壅。",
					"type":"paragraph"
				},
				{
					"detail":"忌破气，升，发散，收涩。",
					"type":"paragraph"
				},
				{
					"detail":"诃子亚芙蓉粟壳（以上收涩）余录后宜降气，消痰，辛凉，甘寒，苦平。",
					"type":"paragraph"
				},
				{
					"detail":"枇杷叶苏子贝母竹沥桑根白栝蒌根款冬花百部百合薄荷天门冬麦门冬马兜铃沙参前胡白前射干",
					"type":"paragraph"
				},
				{
					"detail":"咳嗽",
					"type":"paragraph"
				},
				{
					"detail":"吐血痰并声哑，属肺热甚。",
					"type":"paragraph"
				},
				{
					"detail":"忌升，破气，复忌补气，破血，辛燥，热，收涩。",
					"type":"paragraph"
				},
				{
					"detail":"宜降气清热，润肺生津液，凉血益血，甘寒，甘平，咸寒，佐以苦寒。",
					"type":"paragraph"
				},
				{
					"detail":"生地黄郁金蒲黄柔根白芨阿胶侧柏叶童便知母",
					"type":"paragraph"
				},
				{
					"detail":"肺痿",
					"type":"paragraph"
				},
				{
					"detail":"属肺气虚，有热。",
					"type":"paragraph"
				},
				{
					"detail":"忌宜俱同肺虚。",
					"type":"paragraph"
				},
				{
					"detail":"龟胸",
					"type":"paragraph"
				},
				{
					"detail":"属肺热有痰。",
					"type":"paragraph"
				},
				{
					"detail":"忌宜俱同喘咳嗽。",
					"type":"paragraph"
				},
				{
					"detail":"息贲",
					"type":"paragraph"
				},
				{
					"detail":"属肺气虚，痰热壅结所致。",
					"type":"paragraph"
				},
				{
					"detail":"忌破气，辛热，补敛。",
					"type":"paragraph"
				},
				{
					"detail":"宜降气，清热开痰，佐以散结。",
					"type":"paragraph"
				},
				{
					"detail":"橘皮白豆蔻白芥子旋复花射干桔梗桑白皮参用东垣息贲丸治之。",
					"type":"paragraph"
				},
				{
					"detail":"肾虚",
					"type":"paragraph"
				},
				{
					"detail":"即肾水真阴不足。",
					"type":"paragraph"
				},
				{
					"detail":"忌升，破气，利水，温热，辛燥，补命门相火。",
					"type":"paragraph"
				},
				{
					"detail":"仙茅巴戟天葫芦巴人参补骨脂鹿茸人胞（以上补命门相火）余药录后。",
					"type":"paragraph"
				},
				{
					"detail":"宜滋阴，润，生精补血，除热，甘寒，酸寒，苦寒，咸寒。",
					"type":"paragraph"
				},
				{
					"detail":"地黄牛膝枸杞子人乳肉苁蓉柏子仁胡麻杜仲山茱萸续断天门冬麦门冬知母黄柏五味子鳖甲菟丝子车前子丹参童便地骨皮沙苑蒺藜薯蓣",
					"type":"paragraph"
				},
				{
					"detail":"肾虚腰痛",
					"type":"paragraph"
				},
				{
					"detail":"属精气虚。",
					"type":"paragraph"
				},
				{
					"detail":"忌破气，燥热。",
					"type":"paragraph"
				},
				{
					"detail":"宜同肾虚。",
					"type":"paragraph"
				},
				{
					"detail":"骨乏无力",
					"type":"paragraph"
				},
				{
					"detail":"属阴精不足，肾主骨故也。",
					"type":"paragraph"
				},
				{
					"detail":"忌宜俱同肾虚。",
					"type":"paragraph"
				},
				{
					"detail":"骨蒸潮热",
					"type":"paragraph"
				},
				{
					"detail":"属精血虚极，以致阳无所附，火空上炎。",
					"type":"paragraph"
				},
				{
					"detail":"忌宜俱同肾虚。",
					"type":"paragraph"
				},
				{
					"detail":"传尸痨",
					"type":"paragraph"
				},
				{
					"detail":"忌同肾虚。",
					"type":"paragraph"
				},
				{
					"detail":"宜除热益阴，杀痨虫，兼清镇。",
					"type":"paragraph"
				},
				{
					"detail":"诸药同肾虚，加鬼臼干漆漆叶胡黄连芦荟象胆獭肝安息香丹砂磁石神水",
					"type":"paragraph"
				},
				{
					"detail":"五心烦热",
					"type":"paragraph"
				},
				{
					"detail":"属真阴不足。",
					"type":"paragraph"
				},
				{
					"detail":"忌宜俱同肾虚。",
					"type":"paragraph"
				},
				{
					"detail":"梦遗泄精",
					"type":"paragraph"
				},
				{
					"detail":"属肾虚有火。",
					"type":"paragraph"
				},
				{
					"detail":"忌同肾虚。",
					"type":"paragraph"
				},
				{
					"detail":"宜滋阴，生精补血，除热，酸敛，佐以涩精。",
					"type":"paragraph"
				},
				{
					"detail":"石斛莲花蕊生甘草龙骨鱼胶莲肉牡蛎缩砂密覆盆子远志韭子",
					"type":"paragraph"
				},
				{
					"detail":"小便短涩",
					"type":"paragraph"
				},
				{
					"detail":"热赤频数，属肾虚有火。",
					"type":"paragraph"
				},
				{
					"detail":"忌宜俱同肾虚。",
					"type":"paragraph"
				},
				{
					"detail":"溺有余沥",
					"type":"paragraph"
				},
				{
					"detail":"属气虚。",
					"type":"paragraph"
				},
				{
					"detail":"忌同肾虚。",
					"type":"paragraph"
				},
				{
					"detail":"宜亦同肾虚，以五味子、黄柏、人参为君，加菟丝子、覆盆子为臣，益智为佐。",
					"type":"paragraph"
				},
				{
					"detail":"如觉平日肺家有热，或咳嗽有火者，忌人参，用沙参。",
					"type":"paragraph"
				},
				{
					"detail":"溺血血淋",
					"type":"paragraph"
				},
				{
					"detail":"属肾虚，有火热伤血分。",
					"type":"paragraph"
				},
				{
					"detail":"忌同肾虚。",
					"type":"paragraph"
				},
				{
					"detail":"宜同肾虚，加侧柏叶阿胶茅根韭白干地黄戎盐蒲黄",
					"type":"paragraph"
				},
				{
					"detail":"伤精白浊",
					"type":"paragraph"
				},
				{
					"detail":"属房劳过度，以致精伤流出，似白浊证。",
					"type":"paragraph"
				},
				{
					"detail":"忌利小便，燥，辛热。",
					"type":"paragraph"
				},
				{
					"detail":"宜同肾虚。",
					"type":"paragraph"
				},
				{
					"detail":"五淋",
					"type":"paragraph"
				},
				{
					"detail":"属肾虚，兼有湿热。",
					"type":"paragraph"
				},
				{
					"detail":"忌同肾虚。",
					"type":"paragraph"
				},
				{
					"detail":"宜亦同，加清湿热。",
					"type":"paragraph"
				},
				{
					"detail":"茯苓黄柏车前子石斛萆薏苡仁",
					"type":"paragraph"
				},
				{
					"detail":"精塞水窍不通",
					"type":"paragraph"
				},
				{
					"detail":"属房欲不竟，或思欲不遂，或惧泄忍精，或老人气不足以送精出窍。",
					"type":"paragraph"
				},
				{
					"detail":"忌破气，下，利小便，燥热。",
					"type":"paragraph"
				},
				{
					"detail":"宜行败精，壮实人宜兼泄火，老人宜兼补气血，外治用吮法。",
					"type":"paragraph"
				},
				{
					"detail":"牛膝生地黄当归桃仁车前子鹿角霜红花",
					"type":"paragraph"
				},
				{
					"detail":"齿浮",
					"type":"paragraph"
				},
				{
					"detail":"真牙摇动，及下龈软，或齿衄，属肾虚有热。",
					"type":"paragraph"
				},
				{
					"detail":"忌同肾虚，又忌当归、芎。",
					"type":"paragraph"
				},
				{
					"detail":"宜益阴，凉血，固肾，诸药略同肾虚，应以地黄、黄柏、五味子为君，桑椹、牛膝、沙苑蒺藜、鹿茸、天门冬为臣，龙骨、牡蛎为使。",
					"type":"paragraph"
				},
				{
					"detail":"下消",
					"type":"paragraph"
				},
				{
					"detail":"属肾阴虚，火伏下焦。",
					"type":"paragraph"
				},
				{
					"detail":"忌同肾虚。",
					"type":"paragraph"
				},
				{
					"detail":"宜清热，及峻补真气，润，酸敛，诸药同肾虚，宜以黄柏、五味子、生地黄、天门冬、麦门冬、人参为君，石斛、牛膝、知母、人乳、童便为臣，地骨皮、青蒿、侧柏为佐。",
					"type":"paragraph"
				},
				{
					"detail":"善恐",
					"type":"paragraph"
				},
				{
					"detail":"属肾气虚，肾藏志故也。",
					"type":"paragraph"
				},
				{
					"detail":"忌破气，苦寒，诸药录后。",
					"type":"paragraph"
				},
				{
					"detail":"宜补气强志，辛平，甘温，佐以辛香。",
					"type":"paragraph"
				},
				{
					"detail":"人参远志茯苓酸枣仁柏子仁沉水香鹿茸石斛",
					"type":"paragraph"
				},
				{
					"detail":"阴窍漏气",
					"type":"paragraph"
				},
				{
					"detail":"属肾气虚不固，肾主纳气，虚则不能纳故也。",
					"type":"paragraph"
				},
				{
					"detail":"忌破气，降，香燥，辛热。",
					"type":"paragraph"
				},
				{
					"detail":"苏子郁金降香橘皮沉水香通草（以上降）白豆寇木香香附（以上香燥）余药录后。",
					"type":"paragraph"
				},
				{
					"detail":"宜补真气，酸敛，固涩。",
					"type":"paragraph"
				},
				{
					"detail":"人参五味子山茱萸覆盆子龙骨牡蛎远志枸杞子益智子金樱子沙苑蒺黎莲须参用肾虚条内诸药。",
					"type":"paragraph"
				},
				{
					"detail":"疝",
					"type":"paragraph"
				},
				{
					"detail":"属肾虚，寒湿邪乘虚客之所致。丹溪谓与肾经绝无相干者，误也。又有先因寒邪为病，后成湿热者。药宜分寒热先后二途。",
					"type":"paragraph"
				},
				{
					"detail":"忌升，破气，苦寒，湿润，诸药录后。",
					"type":"paragraph"
				},
				{
					"detail":"宜补气，通肾气，除湿，又有阴虚有热之人病此，兼宜除湿。",
					"type":"paragraph"
				},
				{
					"detail":"人参黄橘核合欢子荔枝核牛膝木瓜杜仲萆川楝子巴戟天虚寒而痛加桂、茴香、补骨脂、仙茅。",
					"type":"paragraph"
				},
				{
					"detail":"虚热而痛加黄柏、车前子、湿盛者加术。",
					"type":"paragraph"
				},
				{
					"detail":"奔豚",
					"type":"paragraph"
				},
				{
					"detail":"属肾虚，脾家湿邪下传客肾所致。",
					"type":"paragraph"
				},
				{
					"detail":"忌同疝，兼忌燥。",
					"type":"paragraph"
				},
				{
					"detail":"宜补气，健脾，辛温，散结。",
					"type":"paragraph"
				},
				{
					"detail":"人参薯蓣桂牛膝山茱萸蛇床子茴香参用东垣奔豚丸治之。",
					"type":"paragraph"
				},
				{
					"detail":"命门虚",
					"type":"paragraph"
				},
				{
					"detail":"即元阳真火不足。（四证）忌下泄，破气，发散，辛寒，苦寒，淡渗，燥，补肾水苦寒药，诸药录后。",
					"type":"paragraph"
				},
				{
					"detail":"黄柏知母生地黄天门冬（以上补肾水苦寒药）宜益真阴之气，甘温，咸温，甘热，酸敛。",
					"type":"paragraph"
				},
				{
					"detail":"人参人胞肉苁蓉菟丝子枸杞子五味石枣鹿茸覆盆子巴戟天补骨脂附子仙茅",
					"type":"paragraph"
				},
				{
					"detail":"阴痿",
					"type":"paragraph"
				},
				{
					"detail":"属命门火衰，下焦虚寒。",
					"type":"paragraph"
				},
				{
					"detail":"忌同命门虚。",
					"type":"paragraph"
				},
				{
					"detail":"宜同命门虚，加海狗肾蛇床子原蚕娥牛膝雀卵狗阴茎",
					"type":"paragraph"
				},
				{
					"detail":"肾泄",
					"type":"paragraph"
				},
				{
					"detail":"即五更及黎明泄泻者是也，亦名大泻泄，属命门真火不足。",
					"type":"paragraph"
				},
				{
					"detail":"忌同命门虚。",
					"type":"paragraph"
				},
				{
					"detail":"宜益火，甘温。",
					"type":"paragraph"
				},
				{
					"detail":"肉豆蔻补骨脂人参薯蓣莲肉砂仁吴茱萸五味子木香",
					"type":"paragraph"
				},
				{
					"detail":"小肠虚遗尿",
					"type":"paragraph"
				},
				{
					"detail":"属小肠气虚，兼肾不足。",
					"type":"paragraph"
				},
				{
					"detail":"忌破气，辛散，燥热。",
					"type":"paragraph"
				},
				{
					"detail":"宜补气，甘温，酸温。",
					"type":"paragraph"
				},
				{
					"detail":"人参黄麦门冬五味子山茱萸遗尿宜固涩，加益智、龙骨、金樱子、牡蛎。",
					"type":"paragraph"
				},
				{
					"detail":"胆虚",
					"type":"paragraph"
				},
				{
					"detail":"（二证）忌汗，下，苦寒，破气，燥，吐。",
					"type":"paragraph"
				},
				{
					"detail":"山栀瓜蒂藜芦盐汤常山（以上吐）余录后宜甘温，甘平，酸敛，佐以微辛。",
					"type":"paragraph"
				},
				{
					"detail":"谷精草人参当归决明子甘草木贼草白芍药竹叶竹茹酸枣仁",
					"type":"paragraph"
				},
				{
					"detail":"病后不得眠",
					"type":"paragraph"
				},
				{
					"detail":"易惊，属胆气虚。",
					"type":"paragraph"
				},
				{
					"detail":"忌破气，升发，燥热。",
					"type":"paragraph"
				},
				{
					"detail":"宜补胆气，甘温，辛温，酸平。",
					"type":"paragraph"
				},
				{
					"detail":"酸枣仁人参甘草竹叶当归竹茹白芍药橘皮",
					"type":"paragraph"
				},
				{
					"detail":"胃虚",
					"type":"paragraph"
				},
				{
					"detail":"（七证）忌下，破气，苦寒，燥热，诸药录后。",
					"type":"paragraph"
				},
				{
					"detail":"宜益气，甘平，甘淡，酸。",
					"type":"paragraph"
				},
				{
					"detail":"人参白术扁豆莲肉石斛橘皮茯苓木瓜芍药兼寒加生姜、白豆寇、缩砂密，兼热加竹茹、枇杷叶、麦门冬、芦根汁、蔗浆。",
					"type":"paragraph"
				},
				{
					"detail":"胃弱不纳食",
					"type":"paragraph"
				},
				{
					"detail":"及不思饮食。",
					"type":"paragraph"
				},
				{
					"detail":"忌宜俱同胃虚，仍分寒热治。",
					"type":"paragraph"
				},
				{
					"detail":"胃虚呕吐",
					"type":"paragraph"
				},
				{
					"detail":"宜分寒热。",
					"type":"paragraph"
				},
				{
					"detail":"忌宜俱同胃虚。",
					"type":"paragraph"
				},
				{
					"detail":"霍乱转筋",
					"type":"paragraph"
				},
				{
					"detail":"属胃虚，猝中邪恶气及毒瓦斯，兼有停滞所致。（转筋与肝经血虚不同。）忌闭气，滞腻，收敛，温补，大热。",
					"type":"paragraph"
				},
				{
					"detail":"宜调气和中，辛散，消导。",
					"type":"paragraph"
				},
				{
					"detail":"繇于暑，必口渴或口干，齿燥口苦，小水短赤。",
					"type":"paragraph"
				},
				{
					"detail":"白梅滑石石膏甘草橘皮丝瓜叶香薷木瓜石斛童溺食盐缩砂密泥浆浓朴白扁豆并叶繇于寒，则小水清白，不渴不热。",
					"type":"paragraph"
				},
				{
					"detail":"缩砂密丁香橘皮藿香甚者加吴茱萸、肉桂，外治用杉木、楠材煎汤浸洗。",
					"type":"paragraph"
				},
				{
					"detail":"绞肠痧",
					"type":"paragraph"
				},
				{
					"detail":"属胃气虚，猝中天地邪恶秽污之气。",
					"type":"paragraph"
				},
				{
					"detail":"忌温补，敛，尤忌火酒、生姜、蒜，及谷气米饮，热汤入口即死。",
					"type":"paragraph"
				},
				{
					"detail":"宜通窍辟恶，辛散，咸寒。",
					"type":"paragraph"
				},
				{
					"detail":"龙脑香苏合香藿香檀香乳香芒硝童便煎药亦宜冷服。",
					"type":"paragraph"
				},
				{
					"detail":"中恶",
					"type":"paragraph"
				},
				{
					"detail":"脑中痛，属胃气虚，恶气客之所致。",
					"type":"paragraph"
				},
				{
					"detail":"忌同绞肠痧。",
					"type":"paragraph"
				},
				{
					"detail":"宜辟恶气，通畅胃气，辛散。",
					"type":"paragraph"
				},
				{
					"detail":"龙脑香檀香麝香（孕妇忌用）牛黄乳香苏合香沉水香丹砂雄黄鬼臼藿香白豆蔻石菖蒲橘皮木香远志干姜桂",
					"type":"paragraph"
				},
				{
					"detail":"反胃",
					"type":"paragraph"
				},
				{
					"detail":"属气虚，中酒属胃弱。",
					"type":"paragraph"
				},
				{
					"detail":"忌破气，升，苦寒，甘，燥热，诸药录后。",
					"type":"paragraph"
				},
				{
					"detail":"宜补气，降气，和胃，清热，酸敛以制肝。",
					"type":"paragraph"
				},
				{
					"detail":"枇杷叶人参苏子橘皮木瓜麦门冬芦根汁竹茹石斛梅酱蔗浆白茯苓白芍药若因虚寒而得者，加生姜、术、白豆蔻。",
					"type":"paragraph"
				},
				{
					"detail":"大肠虚",
					"type":"paragraph"
				},
				{
					"detail":"（四证）忌破气，下，燥热，诸药录后。",
					"type":"paragraph"
				},
				{
					"detail":"宜补气，润燥，甘温。",
					"type":"paragraph"
				},
				{
					"detail":"人参黄麦冬五味白芍炙草",
					"type":"paragraph"
				},
				{
					"detail":"虚热便闭不通",
					"type":"paragraph"
				},
				{
					"detail":"属血虚，津液不足。",
					"type":"paragraph"
				},
				{
					"detail":"忌破气，下，燥热，苦温，损津液。",
					"type":"paragraph"
				},
				{
					"detail":"郁李仁（损津液）宜生津液，润燥，凉血，益血。",
					"type":"paragraph"
				},
				{
					"detail":"生地黄五味麦冬天冬芝麻麻仁肉苁蓉生蜜当归芦荟炙草",
					"type":"paragraph"
				},
				{
					"detail":"虚热滑泄不禁",
					"type":"paragraph"
				},
				{
					"detail":"属气虚。",
					"type":"paragraph"
				},
				{
					"detail":"忌破气，下，湿润，苦寒。",
					"type":"paragraph"
				},
				{
					"detail":"宜补气，升，甘温，酸敛。",
					"type":"paragraph"
				},
				{
					"detail":"人参黄白术炙甘草吴茱萸肉豆蔻莲肉升麻木瓜补骨脂五味子赤石脂",
					"type":"paragraph"
				},
				{
					"detail":"肠鸣脱肛",
					"type":"paragraph"
				},
				{
					"detail":"属气虚，兼有湿热。",
					"type":"paragraph"
				},
				{
					"detail":"忌同大肠虚。",
					"type":"paragraph"
				},
				{
					"detail":"宜补气，升提，除湿热。",
					"type":"paragraph"
				},
				{
					"detail":"人参黄炙草白术莲肉白扁豆升麻干葛柴胡黄柏防风白芍药黄连黄芩樗根白皮外用五倍子敷之。",
					"type":"paragraph"
				},
				{
					"detail":"膀胱虚",
					"type":"paragraph"
				},
				{
					"detail":"（三证）忌破气，燥，利小便。",
					"type":"paragraph"
				},
				{
					"detail":"宜补气，酸敛。",
					"type":"paragraph"
				},
				{
					"detail":"人参五味子山茱萸益智子金樱子",
					"type":"paragraph"
				},
				{
					"detail":"小便不禁",
					"type":"paragraph"
				},
				{
					"detail":"属气血虚。",
					"type":"paragraph"
				},
				{
					"detail":"忌降下，湿润，燥热。",
					"type":"paragraph"
				},
				{
					"detail":"宜同膀胱虚，加牡蛎龙骨鹿茸桑螵蛸鸡频数不能少忍，加麦门冬五味子山茱萸天门冬黄柏柏子仁鳖甲牛膝甘枸杞子",
					"type":"paragraph"
				},
				{
					"detail":"遗尿",
					"type":"paragraph"
				},
				{
					"detail":"属本经气虚，见小肠虚条内。因膀胱虚，亦能致遗尿，故复列此。",
					"type":"paragraph"
				},
				{
					"detail":"忌宜俱见小肠虚。",
					"type":"paragraph"
				},
				{
					"detail":"膀胱虚",
					"type":"paragraph"
				},
				{
					"detail":"忌宜俱同疝。",
					"type":"paragraph"
				},
				{
					"detail":"三焦虚",
					"type":"paragraph"
				},
				{
					"detail":"（二证）忌破气，降，复忌升发，苦寒。",
					"type":"paragraph"
				},
				{
					"detail":"宜补中益气，佐以辛温。",
					"type":"paragraph"
				},
				{
					"detail":"人参黄白术益智子沉香五味子",
					"type":"paragraph"
				},
				{
					"detail":"短气腹寒",
					"type":"paragraph"
				},
				{
					"detail":"属中气虚。",
					"type":"paragraph"
				},
				{
					"detail":"忌宜俱同三焦。",
					"type":"paragraph"
				},
				{
					"detail":"心实",
					"type":"paragraph"
				},
				{
					"detail":"即实火实热。（五证）忌补敛，升，热，温燥。",
					"type":"paragraph"
				},
				{
					"detail":"宜降火清热，苦寒以折之，辛寒以散之，甘寒以缓之，咸寒以润之。",
					"type":"paragraph"
				},
				{
					"detail":"黄连犀角石膏丹砂牡丹皮生甘草滑石竹叶麦冬童便便结燥，加芒硝、大黄，发狂亦如之。",
					"type":"paragraph"
				},
				{
					"detail":"谵语",
					"type":"paragraph"
				},
				{
					"detail":"属心家邪热。舌破，属心火。烦躁，属心家邪热，及心火内炎。（烦属心，躁属肾。）自笑，属心家有热邪。发狂，属心家有邪热甚。",
					"type":"paragraph"
				},
				{
					"detail":"以上忌宜俱同心实。",
					"type":"paragraph"
				},
				{
					"detail":"肝实",
					"type":"paragraph"
				},
				{
					"detail":"（五证）忌补气，升，酸敛，辛热，辛温，燥，诸药录后。",
					"type":"paragraph"
				},
				{
					"detail":"宜清热降气，苦寒，辛寒，甘寒，酸寒。",
					"type":"paragraph"
				},
				{
					"detail":"橘皮青皮苏子黄连龙胆草生甘草黄芩柴胡竹叶黄黛赤芍药",
					"type":"paragraph"
				},
				{
					"detail":"善怒",
					"type":"paragraph"
				},
				{
					"detail":"怒则气上逆，甚则呕血及飧泄。",
					"type":"paragraph"
				},
				{
					"detail":"忌补，升，热燥，闭气，诸药录后。",
					"type":"paragraph"
				},
				{
					"detail":"宜降气，清热，甘寒，酸寒，咸寒，佐以辛散。",
					"type":"paragraph"
				},
				{
					"detail":"苏子郁金青黛麦冬赤芍生甘草橘皮蒲黄当归砂仁香附生地黄童便",
					"type":"paragraph"
				},
				{
					"detail":"善叹息",
					"type":"paragraph"
				},
				{
					"detail":"忽忽不乐，胁痛呕血，属肝气逆，肝火盛，肝血虚。",
					"type":"paragraph"
				},
				{
					"detail":"忌宜俱同善怒。",
					"type":"paragraph"
				},
				{
					"detail":"发搐",
					"type":"paragraph"
				},
				{
					"detail":"属肝家邪热，热则生风，风主掉眩故也。",
					"type":"paragraph"
				},
				{
					"detail":"忌同善怒。",
					"type":"paragraph"
				},
				{
					"detail":"宜清热，降气，利小便，缓中。",
					"type":"paragraph"
				},
				{
					"detail":"黄连芍药丹砂童便生地黄羚羊角苏子麦冬竹叶茯苓生甘草甘菊花木通",
					"type":"paragraph"
				},
				{
					"detail":"目赤肿痛",
					"type":"paragraph"
				},
				{
					"detail":"属血热。",
					"type":"paragraph"
				},
				{
					"detail":"忌同肝实善怒。",
					"type":"paragraph"
				},
				{
					"detail":"宜凉血清热，甘寒，苦寒，酸寒。",
					"type":"paragraph"
				},
				{
					"detail":"生地黄赤芍药谷精草蜜蒙花龙胆草甘草甘菊荆芥黄柏大黄连翘黄连玄参山栀竹叶空青曾青木通童便芒硝蕤核急者宜以三棱针刺破眼眶肿处，捋出热血立解，迟则血贯瞳人目损矣。",
					"type":"paragraph"
				},
				{
					"detail":"脾实",
					"type":"paragraph"
				},
				{
					"detail":"即湿热邪胜。（六证）忌湿润，收涩，滞腻，热，咸，甘，诸药录后。",
					"type":"paragraph"
				},
				{
					"detail":"宜除湿清热，利小便，辛散，风燥，苦寒。",
					"type":"paragraph"
				},
				{
					"detail":"术山栀猪苓泽泻滑石车前茯苓防风干葛黄连枳实白豆蔻",
					"type":"paragraph"
				},
				{
					"detail":"虫胀",
					"type":"paragraph"
				},
				{
					"detail":"繇于脾家，湿热积滞或内伤，瘀血停积而成。",
					"type":"paragraph"
				},
				{
					"detail":"忌破气，甘温，燥热。",
					"type":"paragraph"
				},
				{
					"detail":"宜除湿，清热，利小便，消积。",
					"type":"paragraph"
				},
				{
					"detail":"车前子木通防己猪苓泽泻茯苓鸟喙鱼葶苈山楂红曲三棱蓬术桑白皮",
					"type":"paragraph"
				},
				{
					"detail":"易饥",
					"type":"paragraph"
				},
				{
					"detail":"属脾家邪火。",
					"type":"paragraph"
				},
				{
					"detail":"忌升，辛温，大热，香燥。",
					"type":"paragraph"
				},
				{
					"detail":"沉香麝香龙脑豆蔻藿香缩砂密（以上香燥）宜清火除热，生津液，益脾阴，甘寒，苦寒，酸寒。",
					"type":"paragraph"
				},
				{
					"detail":"黄连青黛连翘山栀麦门冬酸枣仁芍药石膏竹叶石斛",
					"type":"paragraph"
				},
				{
					"detail":"中消",
					"type":"paragraph"
				},
				{
					"detail":"口糜，口唇生疮，属脾家热。",
					"type":"paragraph"
				},
				{
					"detail":"忌温燥，热。",
					"type":"paragraph"
				},
				{
					"detail":"宜甘寒，酸寒，苦寒，辛寒。",
					"type":"paragraph"
				},
				{
					"detail":"麦门冬甘草乌梅黄连黄柏生地黄白芍药玄参连翘干葛石膏龙胆草栝蒌根大青竹叶",
					"type":"paragraph"
				},
				{
					"detail":"湿热腹痛",
					"type":"paragraph"
				},
				{
					"detail":"按之愈甚。",
					"type":"paragraph"
				},
				{
					"detail":"忌闷气，酸敛。温热，燥。",
					"type":"paragraph"
				},
				{
					"detail":"宜利小便，兼升提，苦寒。",
					"type":"paragraph"
				},
				{
					"detail":"滑石木通黄连黄芩升麻柴胡葛根防风车前子不愈加熟大黄，即土郁则夺之义也。",
					"type":"paragraph"
				},
				{
					"detail":"肺热",
					"type":"paragraph"
				},
				{
					"detail":"（八证）忌敛涩，补气，升，燥热，酸，咸。",
					"type":"paragraph"
				},
				{
					"detail":"宜降气，润，甘寒，苦寒，佐以辛散。",
					"type":"paragraph"
				},
				{
					"detail":"枇杷叶苏子桑白皮贝母杏仁白前天门冬前胡车前子知母桑黄石膏栝蒌根黄芩",
					"type":"paragraph"
				},
				{
					"detail":"喘急",
					"type":"paragraph"
				},
				{
					"detail":"属肺有实热，及肺气上逆。",
					"type":"paragraph"
				},
				{
					"detail":"忌同肺实。",
					"type":"paragraph"
				},
				{
					"detail":"宜亦同，加桔梗甘草栝蒌仁玄参青黛",
					"type":"paragraph"
				},
				{
					"detail":"声重",
					"type":"paragraph"
				},
				{
					"detail":"气壅痰稠，属肺热。",
					"type":"paragraph"
				},
				{
					"detail":"忌宜俱同肺热。",
					"type":"paragraph"
				},
				{
					"detail":"喉癣肺胀肺痈",
					"type":"paragraph"
				},
				{
					"detail":"属肺热。",
					"type":"paragraph"
				},
				{
					"detail":"忌同肺实。",
					"type":"paragraph"
				},
				{
					"detail":"宜清热，消痰，降火，解毒散结，甘寒，苦寒，辛寒。",
					"type":"paragraph"
				},
				{
					"detail":"桑白皮桑黄黄芩栝蒌根贝母薏苡仁虎耳草蕺米连翘鼠粘子甘草败酱草",
					"type":"paragraph"
				},
				{
					"detail":"吐脓血血痰，咳嗽嗽血",
					"type":"paragraph"
				},
				{
					"detail":"属肝家火实热甚，此正邪气胜则实之谓。",
					"type":"paragraph"
				},
				{
					"detail":"忌同肺实。",
					"type":"paragraph"
				},
				{
					"detail":"宜清热降气，凉血，豁痰。",
					"type":"paragraph"
				},
				{
					"detail":"枇杷叶桑白皮童便苏子剪草蒲黄麦门冬天门冬百部桑黄百合甘草生地黄薏苡仁贝母白芨桔梗紫菀白芍药款冬花",
					"type":"paragraph"
				},
				{
					"detail":"上消",
					"type":"paragraph"
				},
				{
					"detail":"属肺家实火，及上焦热。",
					"type":"paragraph"
				},
				{
					"detail":"忌同肺实。",
					"type":"paragraph"
				},
				{
					"detail":"宜降气，清热，补肺，生津，甘寒，苦寒，酸寒，辛寒。",
					"type":"paragraph"
				},
				{
					"detail":"苏子桔梗百部百合麦门冬枇杷叶黄芩沙参黄连葛根桑白皮天门冬知母玄参石膏甘草栝蒌根五味子芦根冬瓜人乳白芍药竹叶肾无实，故无泻法。",
					"type":"paragraph"
				},
				{
					"detail":"命门实",
					"type":"paragraph"
				},
				{
					"detail":"（二证）忌补气，温，热。",
					"type":"paragraph"
				},
				{
					"detail":"宜苦寒，甘寒，咸寒。",
					"type":"paragraph"
				},
				{
					"detail":"天门冬麦门冬黄柏知母玄参木通牡丹皮车前子泽泻",
					"type":"paragraph"
				},
				{
					"detail":"强阳不倒",
					"type":"paragraph"
				},
				{
					"detail":"属命门火实，孤阳无阴所致，此证多不治。",
					"type":"paragraph"
				},
				{
					"detail":"忌同命门实。",
					"type":"paragraph"
				},
				{
					"detail":"宜亦同，加五味、童便、生地黄。",
					"type":"paragraph"
				},
				{
					"detail":"水窍涩痛",
					"type":"paragraph"
				},
				{
					"detail":"属命门实火。",
					"type":"paragraph"
				},
				{
					"detail":"忌同命门实。",
					"type":"paragraph"
				},
				{
					"detail":"宜清热，利窍，甘寒，苦寒，咸寒，佐以淡渗。",
					"type":"paragraph"
				},
				{
					"detail":"车前子黄柏知母黄芩牛膝生地黄天门冬甘草童便茯苓木通麦门冬",
					"type":"paragraph"
				},
				{
					"detail":"小肠实",
					"type":"paragraph"
				},
				{
					"detail":"（一证）忌敛涩，补气。",
					"type":"paragraph"
				},
				{
					"detail":"宜通利，淡渗，苦寒，甘寒，咸寒。",
					"type":"paragraph"
				},
				{
					"detail":"车前子茯苓木通黄柏知母生甘草麦门冬黄芩黄连牛膝童溺生地黄",
					"type":"paragraph"
				},
				{
					"detail":"小水不利及赤",
					"type":"paragraph"
				},
				{
					"detail":"或涩痛尿血。",
					"type":"paragraph"
				},
				{
					"detail":"忌宜俱同小肠实。",
					"type":"paragraph"
				},
				{
					"detail":"胆实",
					"type":"paragraph"
				},
				{
					"detail":"（二证）忌汗，吐，下。",
					"type":"paragraph"
				},
				{
					"detail":"宜和解，辛寒，甘寒，苦寒，辛温。",
					"type":"paragraph"
				},
				{
					"detail":"柴胡黄芩半夏生姜甘草龙胆草橘皮",
					"type":"paragraph"
				},
				{
					"detail":"口苦耳聋胁痛",
					"type":"paragraph"
				},
				{
					"detail":"往来寒热。",
					"type":"paragraph"
				},
				{
					"detail":"忌同胆实。",
					"type":"paragraph"
				},
				{
					"detail":"宜用仲景小柴胡汤，随所见兼证加减。",
					"type":"paragraph"
				},
				{
					"detail":"鼻渊",
					"type":"paragraph"
				},
				{
					"detail":"属胆移热于脑。",
					"type":"paragraph"
				},
				{
					"detail":"忌辛温，燥热。",
					"type":"paragraph"
				},
				{
					"detail":"宜清热，补脑，甘寒，甘平，佐以辛寒。",
					"type":"paragraph"
				},
				{
					"detail":"天门冬沙参薄荷柴胡辛夷沙苑蒺藜甘菊花石枣黄芩玄参知母生地黄",
					"type":"paragraph"
				},
				{
					"detail":"胃实",
					"type":"paragraph"
				},
				{
					"detail":"（六证）忌升，补敛，辛温，燥热，湿润。",
					"type":"paragraph"
				},
				{
					"detail":"宜下，如邪未结，宜清热发散，苦寒，辛寒，甘寒。",
					"type":"paragraph"
				},
				{
					"detail":"大黄枳实知母石膏葛根竹叶大青小青青黛麦冬甘草",
					"type":"paragraph"
				},
				{
					"detail":"谵语发狂",
					"type":"paragraph"
				},
				{
					"detail":"发斑，弃衣而走，登高而歌，属胃家邪热实。",
					"type":"paragraph"
				},
				{
					"detail":"忌同胃实。",
					"type":"paragraph"
				},
				{
					"detail":"宜亦同。",
					"type":"paragraph"
				},
				{
					"detail":"如大便结者，加芒硝亟下之。发斑者，加鼠粘子、玄参、栝蒌根，多用石膏为君，便结亦加大黄下之。",
					"type":"paragraph"
				},
				{
					"detail":"嘈杂吞酸",
					"type":"paragraph"
				},
				{
					"detail":"口臭口淡，数欲饮食，属胃火。",
					"type":"paragraph"
				},
				{
					"detail":"忌同胃实。",
					"type":"paragraph"
				},
				{
					"detail":"宜清热降火，苦寒，甘寒，辛寒。",
					"type":"paragraph"
				},
				{
					"detail":"黄连青黛连翘麦冬石斛芦根汁竹叶石膏",
					"type":"paragraph"
				},
				{
					"detail":"呕吐",
					"type":"paragraph"
				},
				{
					"detail":"属胃火者，必面赤，小便短赤，或涩，大便多燥，口苦或干渴。",
					"type":"paragraph"
				},
				{
					"detail":"忌同胃实。",
					"type":"paragraph"
				},
				{
					"detail":"宜亦同，加枇杷叶竹茹木瓜芦根橘皮通草茯苓",
					"type":"paragraph"
				},
				{
					"detail":"大肠实",
					"type":"paragraph"
				},
				{
					"detail":"（四证）忌补敛，燥热。",
					"type":"paragraph"
				},
				{
					"detail":"宜润下，苦寒，辛寒。",
					"type":"paragraph"
				},
				{
					"detail":"麻仁桃仁黄连黄芩槐花生地黄大黄石膏知母枳壳",
					"type":"paragraph"
				},
				{
					"detail":"便硬闭",
					"type":"paragraph"
				},
				{
					"detail":"忌同大肠实。",
					"type":"paragraph"
				},
				{
					"detail":"宜亦同，加芒硝猪胆槟榔郁李仁石蜜",
					"type":"paragraph"
				},
				{
					"detail":"脏毒肠风下血",
					"type":"paragraph"
				},
				{
					"detail":"属大肠湿热。",
					"type":"paragraph"
				},
				{
					"detail":"忌下，燥热。",
					"type":"paragraph"
				},
				{
					"detail":"宜清热，凉血，兼升，甘寒，苦寒。",
					"type":"paragraph"
				},
				{
					"detail":"槐花地榆黄连黄芩生地黄白芍药荆芥防风甘草红曲侧柏叶白头翁蒲黄鸡子葛根",
					"type":"paragraph"
				},
				{
					"detail":"肠痈",
					"type":"paragraph"
				},
				{
					"detail":"属大肠实火。",
					"type":"paragraph"
				},
				{
					"detail":"忌同肠风下血。",
					"type":"paragraph"
				},
				{
					"detail":"宜下，苦寒，解寒。",
					"type":"paragraph"
				},
				{
					"detail":"大黄白芷白芨白蔹白药子忍冬藤连翘甘草黄连黄生地黄天明精明矾黄蜡生蜜（以上三味作丸）",
					"type":"paragraph"
				},
				{
					"detail":"膀胱实",
					"type":"paragraph"
				},
				{
					"detail":"（一证）忌燥热，收涩。",
					"type":"paragraph"
				},
				{
					"detail":"宜润，淡渗。",
					"type":"paragraph"
				},
				{
					"detail":"知母黄柏木通瞿麦车前子滑石茯苓猪苓泽泻",
					"type":"paragraph"
				},
				{
					"detail":"癃闭",
					"type":"paragraph"
				},
				{
					"detail":"属膀胱实热。",
					"type":"paragraph"
				},
				{
					"detail":"忌破气，发散，燥热，如属水液不足，兼忌利小便。",
					"type":"paragraph"
				},
				{
					"detail":"宜同膀胱实，佐以升提，升麻，柴胡。",
					"type":"paragraph"
				},
				{
					"detail":"三焦实",
					"type":"paragraph"
				},
				{
					"detail":"（三证）忌补敛，升，燥热。",
					"type":"paragraph"
				},
				{
					"detail":"宜降，清热，调气，甘寒，苦寒，咸寒。",
					"type":"paragraph"
				},
				{
					"detail":"苏子麦冬知母黄柏玄参山栀黄芩黄连童便",
					"type":"paragraph"
				},
				{
					"detail":"喉痹",
					"type":"paragraph"
				},
				{
					"detail":"即缠喉风，属少阳相火，少阴君火并炽，经曰∶“一阴一阳结为喉痹。”一阴者。少阴君火也。一阳者，少阳相火也。忌同三焦实。",
					"type":"paragraph"
				},
				{
					"detail":"宜辛散，佐以苦寒，咸寒，急则有针、吹、吐三法。",
					"type":"paragraph"
				},
				{
					"detail":"鼠粘子射干黄连黄柏山豆根麦门冬生犀角知母玄参童便山茨菇苦桔梗续随子苏子贝母甘草急治用胆矾、朴硝、牛黄，为末和匀，吹入喉中。又法用明矾三钱，巴豆七粒去壳，同矾，矾枯去巴豆，即取矾为细末，吹入喉中，流出热涎即宽。",
					"type":"paragraph"
				},
				{
					"detail":"头面赤热",
					"type":"paragraph"
				},
				{
					"detail":"属上焦火升。",
					"type":"paragraph"
				},
				{
					"detail":"忌同三焦实。",
					"type":"paragraph"
				},
				{
					"detail":"宜降，清热，甘缓，佐以酸敛。",
					"type":"paragraph"
				},
				{
					"detail":"苏子天冬麦冬玄参薄荷枇杷叶梨柿蔗童便五味栝蒌根芍药",
					"type":"paragraph"
				},
				{
					"detail":"赤白游风",
					"type":"paragraph"
				},
				{
					"detail":"属血热，热则生风，故善游走，俗名火丹。小儿多患此，大人亦时有之。",
					"type":"paragraph"
				},
				{
					"detail":"忌同三焦实。",
					"type":"paragraph"
				},
				{
					"detail":"宜清热，凉血，兼行血，辛寒，甘寒，苦寒，咸寒。",
					"type":"paragraph"
				},
				{
					"detail":"黄连黄柏蒲黄生地黄生甘草牡丹皮连翘玄参牛膝红蓝花鼠粘子赤芍药蓝汁苎根童便牡丹皮宜兼外治，砭出热血，及用漆姑草，慎火草，捣烂敷之，即易愈。",
					"type":"paragraph"
				},
				{
					"detail":"诸疟",
					"type":"paragraph"
				},
				{
					"detail":"热多。",
					"type":"paragraph"
				},
				{
					"detail":"忌辛热。",
					"type":"paragraph"
				},
				{
					"detail":"宜清热。",
					"type":"paragraph"
				},
				{
					"detail":"贝母石膏橘红干葛滑石麦门冬竹叶牛膝知母黄芩柴胡何首乌茯苓乌梅牡蛎鳖甲寒多。",
					"type":"paragraph"
				},
				{
					"detail":"忌苦寒。",
					"type":"paragraph"
				},
				{
					"detail":"宜辛温。",
					"type":"paragraph"
				},
				{
					"detail":"桂枝姜皮白术苍术草豆蔻人参黄当归半夏炙草白豆蔻橘红汗多。",
					"type":"paragraph"
				},
				{
					"detail":"忌散。",
					"type":"paragraph"
				},
				{
					"detail":"宜补敛。",
					"type":"paragraph"
				},
				{
					"detail":"人参白术黄秋冬加桂枝无汗。",
					"type":"paragraph"
				},
				{
					"detail":"忌补敛。",
					"type":"paragraph"
				},
				{
					"detail":"宜疏散。",
					"type":"paragraph"
				},
				{
					"detail":"干葛柴胡石膏羌活姜皮人参苍术疟母忌纯补。",
					"type":"paragraph"
				},
				{
					"detail":"宜补中行滞。",
					"type":"paragraph"
				},
				{
					"detail":"鳖甲射干牡蛎三棱桂缩砂密橘皮青皮人参",
					"type":"paragraph"
				},
				{
					"detail":"诸痢",
					"type":"paragraph"
				},
				{
					"detail":"忌破，闭气，收涩，燥，温热，咸寒，滑腻。",
					"type":"paragraph"
				},
				{
					"detail":"宜清热消积，开胃气，升，利小便。",
					"type":"paragraph"
				},
				{
					"detail":"黄连黄芩白芍红曲山楂广橘红升麻葛根滑石莲肉甘草白扁豆乌梅如胃弱加人参三四钱，莲子四十粒，橘红二钱，升麻二钱。如腹痛，以黄连四钱，白芍三钱，炙草一钱五分，黄柏一钱，升麻七分煎服。如里急，同上药加当归二钱。如后重甚，加槟榔一钱五分，枳壳一钱五分，木香汁七匙。如口渴去木香倍滑石。",
					"type":"paragraph"
				},
				{
					"detail":"如小便赤涩短少，或不利亦倍之。赤多倍乌梅、山楂、红曲，白多加吴茱萸七分。恶心欲呕，即噤口痢，多用人参、莲肉、扁豆、白芍，以绿色升麻七分佐之。久痢不止，加肉豆蔻一钱，人参三钱，砂仁一钱五分，白茯苓二钱。",
					"type":"paragraph"
				},
				{
					"detail":"泄泻",
					"type":"paragraph"
				},
				{
					"detail":"忌湿润，破气，下，苦寒，滑利。",
					"type":"paragraph"
				},
				{
					"detail":"宜安胃（补脾），升，利小便。",
					"type":"paragraph"
				},
				{
					"detail":"人参茯苓莲肉白术升麻车前子橘红藿香木瓜干葛炙草白莱菔扁豆虚寒者，加肉豆、茯苓、补骨脂、吴茱萸。虚热者，去白术加川黄连，倍芍药、莲肉。",
					"type":"paragraph"
				},
				{
					"detail":"暑湿为病，则小水短赤或口渴，倍用姜黄连为君，佐以干葛、升麻。繇于感风寒者，二术、吴茱萸、砂仁、陈皮、干姜、紫苏主之。若繇饮食停滞者，兼消导，山楂、麦芽、神曲、陈皮，肉豆蔻。",
					"type":"paragraph"
				},
				{
					"detail":"诸疸",
					"type":"paragraph"
				},
				{
					"detail":"忌破气，闭气，下，咸，滑利，滞腻，润燥热。有瘀血者，兼忌酸寒。",
					"type":"paragraph"
				},
				{
					"detail":"宜清热，利水，除湿，养胃气。有停滞者，宜消积滞。有瘀血者，宜行血。",
					"type":"paragraph"
				},
				{
					"detail":"茵陈蒿黄连苜蓿（酒疸非此不愈）栀子紫草滑石栝蒌根秦艽车前子白鲜皮黄芩茯苓仙人对坐草连钱草（一名蟹靥草，一名九里香。取汁入姜汁少许，饮之良。）虚者加人参，停滞者加红曲、橘、谷、麦、柏、山楂，瘀血加琥珀、牡丹皮、红曲、红花，桃仁、玄胡索，蒲黄，五灵脂、韭。元气壮实者，服前药，瘀血不行，可加熟地黄，虚勿用。",
					"type":"paragraph"
				},
				{
					"detail":"痰繇于热",
					"type":"paragraph"
				},
				{
					"detail":"忌燥，温热，补敛，升，诸药录后。",
					"type":"paragraph"
				},
				{
					"detail":"宜降，润，清热，苦寒，辛寒，佐以咸寒。",
					"type":"paragraph"
				},
				{
					"detail":"苏子橘红黄芩薄荷枇杷叶桑白皮百部桔梗贝母蛤粉栝蒌根栝蒌仁天冬麦冬竹沥童便胶固者，加霞天膏。",
					"type":"paragraph"
				},
				{
					"detail":"痰繇于风寒",
					"type":"paragraph"
				},
				{
					"detail":"忌补敛，酸，咸，湿润，诸药录后。",
					"type":"paragraph"
				},
				{
					"detail":"宜降气，辛散。",
					"type":"paragraph"
				},
				{
					"detail":"橘红苏子杏仁天麻前胡桑白皮半夏南星葛根薄荷白前生姜汁",
					"type":"paragraph"
				},
				{
					"detail":"痰繇于湿",
					"type":"paragraph"
				},
				{
					"detail":"忌润，咸，酸，滞腻，发散，诸药录后。",
					"type":"paragraph"
				},
				{
					"detail":"宜健脾，燥湿，辛散，佐以淡渗。",
					"type":"paragraph"
				},
				{
					"detail":"人参二术橘红半夏茯苓桑白皮泽泻",
					"type":"paragraph"
				},
				{
					"detail":"饮如涎而薄者",
					"type":"paragraph"
				},
				{
					"detail":"或如涎而稠者，伏于胸中及脾胃间，或吐酸水苦水黄水绿水，或伏而不吐，上支心胸，胃脘作痛，不可忍，按之不得下，或发寒热呕吐不得饮食。",
					"type":"paragraph"
				},
				{
					"detail":"忌宜俱同脾虚证，内停饮条。",
					"type":"paragraph"
				},
				{
					"detail":"诸气",
					"type":"paragraph"
				},
				{
					"detail":"气有余即是火。",
					"type":"paragraph"
				},
				{
					"detail":"忌升，闭气，酸敛，滞腻。",
					"type":"paragraph"
				},
				{
					"detail":"虚者宜降，补敛，调，温，酸，辛，甘。",
					"type":"paragraph"
				},
				{
					"detail":"枇杷叶苏子橘红甘蔗麦门冬芦根汁沉水香白豆蔻郁金甘草童便番降香五味子芍药因虚极而气不得行者，加人参。",
					"type":"paragraph"
				},
				{
					"detail":"实者，宜破散，香燥，辛苦，辛寒。",
					"type":"paragraph"
				},
				{
					"detail":"枳壳青皮槟榔浓朴木香缩砂密沉香香附乌药降香藿香",
					"type":"paragraph"
				},
				{
					"detail":"诸郁",
					"type":"paragraph"
				},
				{
					"detail":"忌酸敛，滞腻，补气，闭气，诸药录后。",
					"type":"paragraph"
				},
				{
					"detail":"属情抱者，宜开发志意，调，散结，和中健脾。",
					"type":"paragraph"
				},
				{
					"detail":"远志贝母郁金香附石菖蒲白豆蔻苏子橘红木香麦冬苏合香缩砂密属五脏者，木郁达之，宜升，吐。",
					"type":"paragraph"
				},
				{
					"detail":"升麻柴胡川芎瓜蒂人参芦火郁发之，宜散。",
					"type":"paragraph"
				},
				{
					"detail":"升麻葛根柴胡防风羌活土郁夺之，宜下。",
					"type":"paragraph"
				},
				{
					"detail":"槟榔枳实浓朴大黄金郁泄之，宜降。",
					"type":"paragraph"
				},
				{
					"detail":"桑白皮赤小豆橘红苏子猪苓泽泻车前子鸟喙鱼木通",
					"type":"paragraph"
				},
				{
					"detail":"关格",
					"type":"paragraph"
				},
				{
					"detail":"忌升，补敛，闭气，酸，诸药录后。",
					"type":"paragraph"
				},
				{
					"detail":"宜降下，辛寒，辛温。",
					"type":"paragraph"
				},
				{
					"detail":"白豆蔻沉香丁香苏子橘红龙脑草苏合香生姜藿香次用大黄车前子黄柏知母滑石木香牛膝",
					"type":"paragraph"
				},
				{
					"detail":"哕症",
					"type":"paragraph"
				},
				{
					"detail":"俗呼呃逆。",
					"type":"paragraph"
				},
				{
					"detail":"忌破气，升，散。",
					"type":"paragraph"
				},
				{
					"detail":"宜补敛，甘温，甘寒。",
					"type":"paragraph"
				},
				{
					"detail":"炙甘草麦门冬人参黄石斛五味子益智子白芍药伤寒失下而发者。",
					"type":"paragraph"
				},
				{
					"detail":"忌补敛，酸，燥热，滞腻，诸药录后。",
					"type":"paragraph"
				},
				{
					"detail":"宜下大小承气之类，便不硬闭，按之腹中和软，未经汗吐者，宜辛寒解表，白虎汤之类。",
					"type":"paragraph"
				},
				{
					"detail":"气逆冲上而发者。",
					"type":"paragraph"
				},
				{
					"detail":"忌升，补，诸药录后。",
					"type":"paragraph"
				},
				{
					"detail":"宜降气，甘寒，咸寒。",
					"type":"paragraph"
				},
				{
					"detail":"枇杷叶芦根汁麦门冬苏子橘红竹茹童便因痰水停膈而发者。",
					"type":"paragraph"
				},
				{
					"detail":"忌升，润，苦寒，甘寒，酸寒，诸药录后。",
					"type":"paragraph"
				},
				{
					"detail":"宜降气，开痰，辛散。",
					"type":"paragraph"
				},
				{
					"detail":"桑白皮苏子贝母橘红半夏旋复花白豆蔻生姜",
					"type":"paragraph"
				},
				{
					"detail":"吐血咯血鼻衄齿衄耳衄舌上出血",
					"type":"paragraph"
				},
				{
					"detail":"忌升提，发散，下，破血，补气，闭气，破气，温热，辛燥，复忌极苦寒伤胃，诸药录后。",
					"type":"paragraph"
				},
				{
					"detail":"宜降气，清热，凉血益阴，兼行血，咸寒，酸寒，甘寒。",
					"type":"paragraph"
				},
				{
					"detail":"苏子天冬麦冬橘皮枇杷叶生地黄降香郁金沙参牛膝熟地黄枸杞子五味阿胶鳖甲青蒿牡丹皮犀角屑芍药剪草童便茅根白药子侧柏叶稷灰藕节当归蒲黄小蓟",
					"type":"paragraph"
				},
				{
					"detail":"蓄血发热",
					"type":"paragraph"
				},
				{
					"detail":"积瘀不行。",
					"type":"paragraph"
				},
				{
					"detail":"忌破气，复忌补气，下，苦寒，辛燥，诸药录后，辛行血，辛温，佐以咸寒。",
					"type":"paragraph"
				},
				{
					"detail":"瘀血行后，宜补血益脾和肝。",
					"type":"paragraph"
				},
				{
					"detail":"红蓝花桃花郁金乳香玄胡索桂（有火勿用）当归尾没药虫蒲黄苏方木番降香穿山甲红曲韭汁童便五灵脂麒麟竭赤芍药桃枭甚者用大黄、花蕊石，瘀行则止，勿过剂。如元气虚，脾胃素弱者，慎勿轻用大黄。",
					"type":"paragraph"
				},
				{
					"detail":"如瘀血行后宜。",
					"type":"paragraph"
				},
				{
					"detail":"生地黄川续断当归身牛膝大黄芍药酸枣仁龙眼肉枸杞子石枣炙草",
					"type":"paragraph"
				},
				{
					"detail":"头痛挟风寒者",
					"type":"paragraph"
				},
				{
					"detail":"忌补敛，诸药录后。",
					"type":"paragraph"
				},
				{
					"detail":"宜辛温发散。",
					"type":"paragraph"
				},
				{
					"detail":"羌活防风细辛蔓荆子荆芥薄荷川芎本升麻白芷生姜葱白",
					"type":"paragraph"
				},
				{
					"detail":"头痛挟邪热者",
					"type":"paragraph"
				},
				{
					"detail":"忌同挟风寒。",
					"type":"paragraph"
				},
				{
					"detail":"宜辛寒，苦寒，解散。",
					"type":"paragraph"
				},
				{
					"detail":"石膏薄荷芽茶黑豆甘菊花土茯苓乌梅黄芩（酒炒）热极目昏便燥者，加酒蒸大黄。",
					"type":"paragraph"
				},
				{
					"detail":"头痛挟痰者",
					"type":"paragraph"
				},
				{
					"detail":"忌升，补敛，酸甘，滞腻，诸药录后。",
					"type":"paragraph"
				},
				{
					"detail":"宜豁痰降气，辛燥。",
					"type":"paragraph"
				},
				{
					"detail":"苏子橘红术贝母半夏前胡竹沥天麻",
					"type":"paragraph"
				},
				{
					"detail":"头痛阴虚者",
					"type":"paragraph"
				},
				{
					"detail":"忌辛热发散，诸药录后。",
					"type":"paragraph"
				},
				{
					"detail":"宜补血益阴，甘寒，酸寒。",
					"type":"paragraph"
				},
				{
					"detail":"生地黄甘菊花当归黄柏天门冬麦门冬枸杞子忍冬乌梅白芍五味子",
					"type":"paragraph"
				},
				{
					"detail":"眉棱骨痛",
					"type":"paragraph"
				},
				{
					"detail":"忌宜俱同阴虚。",
					"type":"paragraph"
				},
				{
					"detail":"齿痛",
					"type":"paragraph"
				},
				{
					"detail":"忌升，补敛，燥热，辛温，诸药录后。",
					"type":"paragraph"
				},
				{
					"detail":"宜清热凉血，苦寒，甘寒，辛寒，咸寒。",
					"type":"paragraph"
				},
				{
					"detail":"竹叶知母黄连黄芩麦门冬生地黄黄柏玄参石膏薄荷赤芍药牡丹皮苏子甘草童便上下龈，属胃与大肠火。",
					"type":"paragraph"
				},
				{
					"detail":"宜熟地黄石膏黄芩黄连麦门冬赤芍药青黛细辛甘草薄荷生地黄枇杷叶苏子木通西瓜皮灰真牙浮动及黑烂，属肾虚有火，已见肾虚条内，忌宜俱同。",
					"type":"paragraph"
				},
				{
					"detail":"胃脘痛",
					"type":"paragraph"
				},
				{
					"detail":"因火者。",
					"type":"paragraph"
				},
				{
					"detail":"忌补敛，燥热，诸药录后。",
					"type":"paragraph"
				},
				{
					"detail":"宜降苦寒，甘寒，咸寒，辛寒。",
					"type":"paragraph"
				},
				{
					"detail":"苏子橘红黄连山栀麦门冬炙甘草石膏知母玄参童便因寒者。",
					"type":"paragraph"
				},
				{
					"detail":"忌破气，滞腻，苦寒，诸药录后。",
					"type":"paragraph"
				},
				{
					"detail":"宜辛温发散。",
					"type":"paragraph"
				},
				{
					"detail":"草豆蔻橘红益智丁香桂白术白蔻吴萸浓朴香附干姜缩砂密藿香因宿食者。",
					"type":"paragraph"
				},
				{
					"detail":"忌升，补敛，苦寒，诸药录后。",
					"type":"paragraph"
				},
				{
					"detail":"宜消导，兼降气，因脾胃虚弱食停者消导。",
					"type":"paragraph"
				},
				{
					"detail":"加人参山楂草果红曲草豆蔻谷麦枳实槟榔青皮浓朴术缩砂密橘皮因瘀血者。",
					"type":"paragraph"
				},
				{
					"detail":"忌补气，酸敛，诸药录后。",
					"type":"paragraph"
				},
				{
					"detail":"宜辛温，苦温以行血。",
					"type":"paragraph"
				},
				{
					"detail":"桃仁红曲红花韭菜玄胡索山楂肉郁金肉桂三棱童便牡丹皮赤芍药通草牛膝琥珀因血虚者，按之则痛止。",
					"type":"paragraph"
				},
				{
					"detail":"忌破气，复忌补气，燥热，辛温。",
					"type":"paragraph"
				},
				{
					"detail":"宜润，补敛，甘寒，甘温。",
					"type":"paragraph"
				},
				{
					"detail":"石斛麦门冬炙甘草酸枣仁白芍药当归生地黄因虫者。",
					"type":"paragraph"
				},
				{
					"detail":"忌补，升，发散，甘，诸药录后。",
					"type":"paragraph"
				},
				{
					"detail":"宜杀虫，苦，酸。",
					"type":"paragraph"
				},
				{
					"detail":"苦楝根使君子薏苡仁根锡灰槟榔鹤虱雷丸芜荑大黄乌梅因恼怒者。",
					"type":"paragraph"
				},
				{
					"detail":"虚弱人忌破气，壮实人忌补气，总忌酸敛，升，诸药录后。",
					"type":"paragraph"
				},
				{
					"detail":"宜降气，辛温。",
					"type":"paragraph"
				},
				{
					"detail":"枇杷叶白豆蔻番降香苏子木香橘红缩砂密玄胡索五灵脂因痰饮者。",
					"type":"paragraph"
				},
				{
					"detail":"忌宜俱见痰饮证下。",
					"type":"paragraph"
				},
				{
					"detail":"腹痛因于寒",
					"type":"paragraph"
				},
				{
					"detail":"忌苦寒，下利，诸药录后。",
					"type":"paragraph"
				},
				{
					"detail":"宜温中，辛散。",
					"type":"paragraph"
				},
				{
					"detail":"白术浓朴吴茱萸缩砂密干姜桂木香橘皮炙甘草因于热，火在少腹则绞痛。",
					"type":"paragraph"
				},
				{
					"detail":"忌辛散，香燥，补敛，诸药录后。",
					"type":"paragraph"
				},
				{
					"detail":"宜甘，苦寒。",
					"type":"paragraph"
				},
				{
					"detail":"山栀仁麦门冬石斛白芍药甘草桔梗黄芩黄连滑石木通戎盐",
					"type":"paragraph"
				},
				{
					"detail":"诸痛不可按",
					"type":"paragraph"
				},
				{
					"detail":"属实。",
					"type":"paragraph"
				},
				{
					"detail":"忌补气，大热，诸药录后。",
					"type":"paragraph"
				},
				{
					"detail":"宜破散，疏利，苦寒。",
					"type":"paragraph"
				},
				{
					"detail":"枳实青皮蓬莪槟榔三棱滑石木通大黄（有积滞宜用，无者勿用。）",
					"type":"paragraph"
				},
				{
					"detail":"诸痛可按",
					"type":"paragraph"
				},
				{
					"detail":"属虚。",
					"type":"paragraph"
				},
				{
					"detail":"忌破气，破血，下利，发散，诸药录后。",
					"type":"paragraph"
				},
				{
					"detail":"宜补气血，甘温，酸敛。",
					"type":"paragraph"
				},
				{
					"detail":"人参黄生地黄二术当归炙草白芍薯蓣枣仁五味",
					"type":"paragraph"
				},
				{
					"detail":"痹",
					"type":"paragraph"
				},
				{
					"detail":"拘挛而痛也。因风寒湿三者合而成，风气胜者为行痹，寒气胜者为痛痹，湿气胜者为着痹。",
					"type":"paragraph"
				},
				{
					"detail":"忌下，收敛，酸寒，苦寒，咸寒，诸药录后。",
					"type":"paragraph"
				},
				{
					"detail":"宜辛散，行气，燥湿，甘寒，淡渗。",
					"type":"paragraph"
				},
				{
					"detail":"漆叶续断黄萆甘菊花车前子甘草防己白术防风桑寄生蔓荆实羌活独活牛膝秦艽白藓皮原蚕沙木瓜天麻泽泻茯苓威灵仙海风藤菖蒲狗脊杜仲石斛细辛松节松叶",
					"type":"paragraph"
				},
				{
					"detail":"痿",
					"type":"paragraph"
				},
				{
					"detail":"属湿热，经曰∶治痿独取阳明。",
					"type":"paragraph"
				},
				{
					"detail":"忌破气，升，辛热，发散。",
					"type":"paragraph"
				},
				{
					"detail":"宜大补气血，清热除湿，甘寒，甘温，苦寒，酸寒。",
					"type":"paragraph"
				},
				{
					"detail":"人参黄二术麦冬炙甘草生地黄木瓜石斛薏苡黄柏白芍药车前子茯苓木通黄芩川黄连",
					"type":"paragraph"
				},
				{
					"detail":"交肠",
					"type":"paragraph"
				},
				{
					"detail":"其病大小便易位而出，或因大怒，或因醉饱，遂至脏气乖乱，不循常道，法当宣吐以开提其气，使HT门清利，得司秘别职则愈矣。",
					"type":"paragraph"
				},
				{
					"detail":"忌破气，燥热，诸药录后。",
					"type":"paragraph"
				},
				{
					"detail":"宜升清降浊，兼补气，淡渗。",
					"type":"paragraph"
				},
				{
					"detail":"升麻柴胡苏子降香橘红人参术茯苓泽泻猪苓木通滑石车前子",
					"type":"paragraph"
				},
				{
					"detail":"鬼疰尸疰飞尸客忤",
					"type":"paragraph"
				},
				{
					"detail":"此系天地阴邪杀厉之气，乘虚中人，或遍身青黯，或忽消瘦声哑，面色青黄不定，或忽惊厥，目直视，手握拳，或遍身骨节疼痛非常。",
					"type":"paragraph"
				},
				{
					"detail":"忌破气，复忌补气，升，燥热，酸敛，诸药录后。",
					"type":"paragraph"
				},
				{
					"detail":"宜辟恶气，安神镇心，辛香发散，金石镇坠。",
					"type":"paragraph"
				},
				{
					"detail":"牛黄丹砂琥珀乳香苏合香天竺黄檀香木香麝香沉香龙脑香安息香真珠雄黄犀角金银箔代赭石虎骨獭肝远志生地黄龙齿天灵盖菖蒲",
					"type":"paragraph"
				},
				{
					"type":"section",
					"title":"诸病应忌药总例",
					"content":[
						{
							"detail":"补气",
							"type":"paragraph"
						},
						{
							"detail":"人参黄二术人胞红铅",
							"type":"paragraph"
						},
						{
							"detail":"温补",
							"type":"paragraph"
						},
						{
							"detail":"人胞红铅白胶鹿茸人参巴戟天黄白术淫羊藿肉苁蓉补骨脂当归狗阴茎菟丝子蛇床子",
							"type":"paragraph"
						},
						{
							"detail":"大热",
							"type":"paragraph"
						},
						{
							"detail":"附子肉佳仙茅乌头阳起石海狗肾硫黄羊肉雀肉天雄葫芦巴",
							"type":"paragraph"
						},
						{
							"detail":"破气",
							"type":"paragraph"
						},
						{
							"detail":"青皮枳实枳壳槟榔浓朴牵牛",
							"type":"paragraph"
						},
						{
							"detail":"闭气",
							"type":"paragraph"
						},
						{
							"detail":"银杏二术黄米曲食猪脂油",
							"type":"paragraph"
						},
						{
							"detail":"降气",
							"type":"paragraph"
						},
						{
							"detail":"苏子郁金橘红沉香枇杷叶降真香乌药",
							"type":"paragraph"
						},
						{
							"detail":"破血",
							"type":"paragraph"
						},
						{
							"detail":"桃仁红花干漆乳香苏方木玄胡索没药姜黄三棱蓬莪五灵脂花蕊石水蛙虻虫肉桂穿山甲麒麟竭虫",
							"type":"paragraph"
						},
						{
							"detail":"升提发散",
							"type":"paragraph"
						},
						{
							"detail":"升麻柴胡川芎紫苏麻黄干葛羌活独活防风白芷生姜细辛荆芥前胡本葱白薄荷",
							"type":"paragraph"
						},
						{
							"detail":"辛温辛热发散",
							"type":"paragraph"
						},
						{
							"detail":"干姜桂枝麻黄吴萸细辛羌活独活防风本川芎白芷葱白",
							"type":"paragraph"
						},
						{
							"detail":"吐",
							"type":"paragraph"
						},
						{
							"detail":"瓜蒂栀子豉人参芦皂荚藜芦常山虾汁盐汤",
							"type":"paragraph"
						},
						{
							"detail":"下",
							"type":"paragraph"
						},
						{
							"detail":"大黄芒硝巴豆牵牛枳实玄明粉浓朴",
							"type":"paragraph"
						},
						{
							"detail":"降泄",
							"type":"paragraph"
						},
						{
							"detail":"山栀知母玄参天冬",
							"type":"paragraph"
						},
						{
							"detail":"利水",
							"type":"paragraph"
						},
						{
							"detail":"猪苓泽泻木通瞿麦葶苈海金沙滑石商陆茯苓蓄琥珀乌根皮芫花甘遂大戟车前续随子汉防己郁李仁",
							"type":"paragraph"
						},
						{
							"detail":"损津液",
							"type":"paragraph"
						},
						{
							"detail":"郁李仁白矾红矾半夏",
							"type":"paragraph"
						},
						{
							"detail":"敛摄",
							"type":"paragraph"
						},
						{
							"detail":"白芍五味醋乌梅白梅酸枣仁",
							"type":"paragraph"
						},
						{
							"detail":"固涩",
							"type":"paragraph"
						},
						{
							"detail":"龙骨牡蛎粟壳益智山茱萸桑螵峭肉果蛇床子阿芙蓉金樱子原蚕娥莲须诃黎勒",
							"type":"paragraph"
						},
						{
							"detail":"消导",
							"type":"paragraph"
						},
						{
							"detail":"山楂麦芽草果槟榔三棱蓬莪神曲枳壳枳实绿矾红曲橘红莱菔子砂仁",
							"type":"paragraph"
						},
						{
							"detail":"开窍",
							"type":"paragraph"
						},
						{
							"detail":"麝香檀香龙脑香苏合香安息香",
							"type":"paragraph"
						},
						{
							"detail":"香燥",
							"type":"paragraph"
						},
						{
							"detail":"沉香麝香豆蔻龙脑香缩砂密藿香香附丁香乌药木香",
							"type":"paragraph"
						},
						{
							"detail":"辛燥",
							"type":"paragraph"
						},
						{
							"detail":"火酒蒜半夏南星二术",
							"type":"paragraph"
						},
						{
							"detail":"辛热",
							"type":"paragraph"
						},
						{
							"detail":"干姜胡椒巴豆吴萸茴香龙脑香",
							"type":"paragraph"
						},
						{
							"detail":"湿润",
							"type":"paragraph"
						},
						{
							"detail":"地黄当归天冬知母肉苁蓉栝蒌仁猪脂麻仁",
							"type":"paragraph"
						},
						{
							"detail":"滞腻",
							"type":"paragraph"
						},
						{
							"detail":"猪羊犬鹅肉地黄南面油腻炙爆",
							"type":"paragraph"
						},
						{
							"detail":"滑利",
							"type":"paragraph"
						},
						{
							"detail":"榆皮牛乳柿瓜李冬葵子桃梨蜜青菜菜酥椿根白皮茄子",
							"type":"paragraph"
						},
						{
							"detail":"发湿",
							"type":"paragraph"
						},
						{
							"detail":"鳜鱼南面",
							"type":"paragraph"
						},
						{
							"detail":"苦寒伤胃",
							"type":"paragraph"
						},
						{
							"detail":"山栀黄柏黄芩黄连大黄苦参玄参知母芦荟",
							"type":"paragraph"
						},
						{
							"detail":"补命门相火",
							"type":"paragraph"
						},
						{
							"detail":"鹿茸附子红铅巴戟天阳起石白胶人胞肉桂仙茅淫羊藿腽肭脐补骨脂狗阴茎菟丝子原蚕蛾",
							"type":"paragraph"
						},
						{
							"detail":"补肾水苦寒",
							"type":"paragraph"
						},
						{
							"detail":"黄柏玄参知母天门冬",
							"type":"paragraph"
						},
						{
							"detail":"酸寒",
							"type":"paragraph"
						},
						{
							"detail":"牛膝乌梅芍药",
							"type":"paragraph"
						},
						{
							"detail":"咸寒",
							"type":"paragraph"
						},
						{
							"detail":"童便芒硝玄参秋石",
							"type":"paragraph"
						},
						{
							"detail":"生冷",
							"type":"paragraph"
						},
						{
							"detail":"菱梨菜李",
							"type":"paragraph"
						},
						{
							"detail":"甘",
							"type":"paragraph"
						},
						{
							"detail":"甘草饴糖大枣蜜",
							"type":"paragraph"
						},
						{
							"detail":"咸",
							"type":"paragraph"
						},
						{
							"detail":"食盐商陆碱水鹿茸蛤蜊蛏蛎黄",
							"type":"paragraph"
						}
					]
				}
			]
		}
	]
}